{"user": "alhllwy", "meta": {"type": "FeatureCollection", "features": [{"type": "Feature", "properties": {"cluster": 0, "clusterCenter": true, "tweetCount": 4, "likelyHome": true}, "geometry": {"type": "Point", "coordinates": [-95.34660839, 29.98687281]}}, {"type": "Feature", "properties": {"cluster": 0, "tweetCount": 4}, "geometry": {"type": "Polygon", "coordinates": [[[-95.34541828, 29.98637061], [-95.34774, 29.9872], [-95.34553528, 29.98672063], [-95.34541828, 29.98637061]]]}}, {"type": "Feature", "properties": {"cluster": 1, "clusterCenter": true, "tweetCount": 3, "likelyWork": true}, "geometry": {"type": "Point", "coordinates": [-95.00264537, 30.046740689999996]}}]}, "tweets": {"type": "FeatureCollection", "features": [{"type": "Feature", "properties": {"tweetID": "900896846142427136", "user": "alhllwy", "text": "I'm at George Bush Intercontinental Airport in Houston, TX w/ @sluffsstelling https://t.co/YdPlVLZukr", "date": "2017-08-25T01:45:20.000Z", "speed": "", "timeD": "", "cluster": 0, "dbscan": "core", "dateStr": "2017-08-25T01:45:20.000Z", "timestamp": 1503625520}, "geometry": {"type": "Point", "coordinates": [-95.34774, 29.9872]}}, {"type": "Feature", "properties": {"tweetID": "901119059655356418", "user": "alhllwy", "text": "I'm at Hardin, Tx in TX w/ @sluffsstelling https://t.co/gkpFBS7uEj", "date": "2017-08-25T16:28:20.000Z", "speed": 2.590461324301954, "timeD": "", "dbscan": "noise", "dateStr": "2017-08-25T16:28:20.000Z", "timestamp": 1503678500, "timeDelta": 52980}, "geometry": {"type": "Point", "coordinates": [-94.73331335, 30.13367247]}}, {"type": "Feature", "properties": {"tweetID": "901171429709930498", "user": "alhllwy", "text": "I'm at Emily &amp; Rachel's \ud83d\ude0d in Dayton, TX https://t.co/D3LdQgWzI2", "date": "2017-08-25T19:56:26.000Z", "speed": 4.9564056700724235, "timeD": "", "cluster": 1, "dbscan": "core", "dateStr": "2017-08-25T19:56:26.000Z", "timestamp": 1503690986, "timeDelta": 12486}, "geometry": {"type": "Point", "coordinates": [-95.00264537, 30.04674069]}}, {"type": "Feature", "properties": {"tweetID": "901230656272945154", "user": "alhllwy", "text": "I'm at Iguana Joes in Baytown, TX w/ @sluffsstelling https://t.co/88WfgiYnWI", "date": "2017-08-25T23:51:47.000Z", "speed": 4.2136894009038075, "timeD": "", "dbscan": "noise", "dateStr": "2017-08-25T23:51:47.000Z", "timestamp": 1503705107, "timeDelta": 14121}, "geometry": {"type": "Point", "coordinates": [-94.89759423, 29.82560567]}}, {"type": "Feature", "properties": {"tweetID": "901448159242727428", "user": "alhllwy", "text": "I was at George Bush Intercontinental Airport in Houston, TX https://t.co/2eBEJQ3uDb", "date": "2017-08-26T14:16:03.000Z", "speed": 2.0264670641862654, "timeD": "", "cluster": 0, "dbscan": "core", "dateStr": "2017-08-26T14:16:03.000Z", "timestamp": 1503756963, "timeDelta": 51856}, "geometry": {"type": "Point", "coordinates": [-95.34774, 29.9872]}}, {"type": "Feature", "properties": {"tweetID": "901456397824667649", "user": "alhllwy", "text": "I'm at Terminal B - @united in Houston, TX https://t.co/FMQQ7Hs7OE", "date": "2017-08-26T14:48:48.000Z", "speed": 0.27543776924536023, "timeD": "", "cluster": 0, "dbscan": "core", "dateStr": "2017-08-26T14:48:48.000Z", "timestamp": 1503758928, "timeDelta": 1965}, "geometry": {"type": "Point", "coordinates": [-95.34541828, 29.98637061]}}, {"type": "Feature", "properties": {"tweetID": "901456465608802304", "user": "alhllwy", "text": "I'm at Peet's Coffee &amp; Tea in Houston, TX https://t.co/ZPh8NoWrir", "date": "2017-08-26T14:49:04.000Z", "speed": 5.666660355123479, "timeD": "", "cluster": 0, "dbscan": "core", "dateStr": "2017-08-26T14:49:04.000Z", "timestamp": 1503758944, "timeDelta": 16}, "geometry": {"type": "Point", "coordinates": [-95.34553528, 29.98672063]}}, {"type": "Feature", "properties": {"tweetID": "901492380246921217", "user": "alhllwy", "text": "Hurricane Harvey hates me, apparently. (@ Emily &amp; Rachel's \ud83d\ude0d in Dayton, TX) https://t.co/YZEsbDK6lO", "date": "2017-08-26T17:11:47.000Z", "speed": 8.801537646758451, "timeD": "", "cluster": 1, "dbscan": "core", "dateStr": "2017-08-26T17:11:47.000Z", "timestamp": 1503767507, "timeDelta": 8563}, "geometry": {"type": "Point", "coordinates": [-95.00264537, 30.04674069]}}, {"type": "Feature", "properties": {"tweetID": "901699349419307008", "user": "alhllwy", "text": "I'm at Momma's Place in Dayton, TX https://t.co/5ezDfPrhY4", "date": "2017-08-27T06:54:12.000Z", "speed": 0.4551109450335268, "timeD": "", "dbscan": "noise", "dateStr": "2017-08-27T06:54:12.000Z", "timestamp": 1503816852, "timeDelta": 49345}, "geometry": {"type": "Point", "coordinates": [-94.8987523, 30.03911351]}}, {"type": "Feature", "properties": {"tweetID": "902292259072339973", "user": "alhllwy", "text": "I'm at Brookshire Brothers in Dayton, TX w/ @sluffsstelling https://t.co/asOGg5h0ET", "date": "2017-08-28T22:10:12.000Z", "speed": 0.024787986675747692, "timeD": "", "dbscan": "noise", "dateStr": "2017-08-28T22:10:12.000Z", "timestamp": 1503958212, "timeDelta": 141360}, "geometry": {"type": "Point", "coordinates": [-94.88496602, 30.04659052]}}, {"type": "Feature", "properties": {"tweetID": "902305341261570048", "user": "alhllwy", "text": "I'm at Emily &amp; Rachel's \ud83d\ude0d in Dayton, TX w/ @sluffsstelling https://t.co/0Q4gdGvIvo", "date": "2017-08-28T23:02:12.000Z", "speed": 8.123578727525677, "timeD": "", "cluster": 1, "dbscan": "core", "dateStr": "2017-08-28T23:02:12.000Z", "timestamp": 1503961332, "timeDelta": 3120}, "geometry": {"type": "Point", "coordinates": [-95.00264537, 30.04674069]}}, {"type": "Feature", "properties": {"tweetID": "902602500133539842", "user": "alhllwy", "text": "I'm at Cove in TX https://t.co/SdgJwa0ngv", "date": "2017-08-29T18:43:00.000Z", "speed": 0.9604290977190219, "timeD": "", "dbscan": "noise", "dateStr": "2017-08-29T18:43:00.000Z", "timestamp": 1504032180, "timeDelta": 70848}, "geometry": {"type": "Point", "coordinates": [-94.81146838, 29.82915626]}}]}}