{"user": "diogoresteves", "meta": {"type": "FeatureCollection", "features": [{"type": "Feature", "properties": {"cluster": 0, "clusterCenter": true, "tweetCount": 7, "likelyHome": true, "likelyWork": true}, "geometry": {"type": "Point", "coordinates": [-81.37580000000001, 28.5335]}}]}, "tweets": {"type": "FeatureCollection", "features": [{"type": "Feature", "properties": {"tweetID": "903436319346524160", "user": "diogoresteves", "text": "Sempre bom fazer novas conex\u00f5es! @ Orlando - Metrowest https://t.co/MsZVxbi6bG", "date": "2017-09-01T01:56:18.000Z", "speed": "", "timeD": "", "dbscan": "noise", "dateStr": "2017-09-01T01:56:18.000Z", "timestamp": 1504230978}, "geometry": {"type": "Point", "coordinates": [-81.456513, 28.513954]}}, {"type": "Feature", "properties": {"tweetID": "903692596823945216", "user": "diogoresteves", "text": "Uma palavra para voc\u00ea focar hoje:\nRELACIONAMENTOS\n\nFica a dica :-) @ Orlando, Florida https://t.co/trqHLCBQPw", "date": "2017-09-01T18:54:39.000Z", "speed": 0.2995508638822617, "timeD": "", "cluster": 0, "dbscan": "core", "dateStr": "2017-09-01T18:54:39.000Z", "timestamp": 1504292079, "timeDelta": 61101}, "geometry": {"type": "Point", "coordinates": [-81.3758, 28.5335]}}, {"type": "Feature", "properties": {"tweetID": "904139625349959680", "user": "diogoresteves", "text": "E hoje faz exatamente um ano, ent\u00e3o... eu perdoou :-) @ Sky Lake, Florida https://t.co/W0w8mYqYV2", "date": "2017-09-03T00:30:59.000Z", "speed": 0.17273762576288348, "timeD": "", "dbscan": "noise", "dateStr": "2017-09-03T00:30:59.000Z", "timestamp": 1504398659, "timeDelta": 106580}, "geometry": {"type": "Point", "coordinates": [-81.39166667, 28.46083333]}}, {"type": "Feature", "properties": {"tweetID": "904372274756804608", "user": "diogoresteves", "text": "Come\u00e7ando a semana com o p\u00e9 direito @firstorlando @ First Baptist Orlando https://t.co/rFsXWcpRLd", "date": "2017-09-03T15:55:27.000Z", "speed": 0.262037602220811, "timeD": "", "dbscan": "noise", "dateStr": "2017-09-03T15:55:27.000Z", "timestamp": 1504454127, "timeDelta": 55468}, "geometry": {"type": "Point", "coordinates": [-81.42309429, 28.51230572]}}, {"type": "Feature", "properties": {"tweetID": "905230300179034112", "user": "diogoresteves", "text": "E essa \u00e9 a primeira parte de alcan\u00e7ar os objetivos...\n\nUma meta n\u00e3o \u00e9 meta de verdade at\u00e9 que\u2026 https://t.co/Z2JW7qPYJt", "date": "2017-09-06T00:44:56.000Z", "speed": 0.05673590529984668, "timeD": "", "cluster": 0, "dbscan": "core", "dateStr": "2017-09-06T00:44:56.000Z", "timestamp": 1504658696, "timeDelta": 204569}, "geometry": {"type": "Point", "coordinates": [-81.3758, 28.5335]}}, {"type": "Feature", "properties": {"tweetID": "905535090771550208", "user": "diogoresteves", "text": "Minha gata linda.\n\nAlgu\u00e9m precisando de guia tur\u00edstico na Disney? Ela quase n\u00e3o gosta quando os\u2026 https://t.co/zkEvpZZjhu", "date": "2017-09-06T20:56:04.000Z", "speed": 0, "timeD": "", "cluster": 0, "dbscan": "core", "dateStr": "2017-09-06T20:56:04.000Z", "timestamp": 1504731364, "timeDelta": 72668}, "geometry": {"type": "Point", "coordinates": [-81.3758, 28.5335]}}, {"type": "Feature", "properties": {"tweetID": "905880592629293056", "user": "diogoresteves", "text": "**Por favor, preste muita aten\u00e7\u00e3o antes de responder esse post e procure interpretar da maneira\u2026 https://t.co/ARQhq8IwZx", "date": "2017-09-07T19:48:58.000Z", "speed": 0, "timeD": "", "cluster": 0, "dbscan": "core", "dateStr": "2017-09-07T19:48:58.000Z", "timestamp": 1504813738, "timeDelta": 82374}, "geometry": {"type": "Point", "coordinates": [-81.3758, 28.5335]}}, {"type": "Feature", "properties": {"tweetID": "906166930045796353", "user": "diogoresteves", "text": "Em uma palavra... o que isso significaria para voc\u00ea? @ Porsche of Orlando https://t.co/EVnTkvO45i", "date": "2017-09-08T14:46:46.000Z", "speed": 0.401801768963678, "timeD": "", "dbscan": "noise", "dateStr": "2017-09-08T14:46:46.000Z", "timestamp": 1504882006, "timeDelta": 68268}, "geometry": {"type": "Point", "coordinates": [-81.355956, 28.642358]}}, {"type": "Feature", "properties": {"tweetID": "906520961213747200", "user": "diogoresteves", "text": "**Pergunta important\u00edssima no final do post.**\n\nBom dia pessoal!\n\nPrimeiro gostaria de agradecer\u2026 https://t.co/ZUmgiNaozn", "date": "2017-09-09T14:13:34.000Z", "speed": 0.32497160415615073, "timeD": "", "cluster": 0, "dbscan": "core", "dateStr": "2017-09-09T14:13:34.000Z", "timestamp": 1504966414, "timeDelta": 84408}, "geometry": {"type": "Point", "coordinates": [-81.3758, 28.5335]}}, {"type": "Feature", "properties": {"tweetID": "906885782996082689", "user": "diogoresteves", "text": "Algu\u00e9m por a\u00ed j\u00e1 passou por um furac\u00e3o? N\u00e3o estou dizendo apenas um furac\u00e3o \"natural\", mas\u2026 https://t.co/co5Ctt8lk8", "date": "2017-09-10T14:23:14.000Z", "speed": 0, "timeD": "", "cluster": 0, "dbscan": "core", "dateStr": "2017-09-10T14:23:14.000Z", "timestamp": 1505053394, "timeDelta": 86980}, "geometry": {"type": "Point", "coordinates": [-81.3758, 28.5335]}}, {"type": "Feature", "properties": {"tweetID": "907092833366151168", "user": "diogoresteves", "text": "As meninas est\u00e3o se preparando para a Irma :-) @ Orlando, Florida https://t.co/SfTjlRXvcu", "date": "2017-09-11T04:05:59.000Z", "speed": 0, "timeD": "", "cluster": 0, "dbscan": "core", "dateStr": "2017-09-11T04:05:59.000Z", "timestamp": 1505102759, "timeDelta": 49365}, "geometry": {"type": "Point", "coordinates": [-81.3758, 28.5335]}}]}}