{"user": "IslesMarina", "meta": {"type": "FeatureCollection", "features": [{"type": "Feature", "properties": {"cluster": 0, "clusterCenter": true, "tweetCount": 110, "likelyHome": true, "likelyWork": true}, "geometry": {"type": "Point", "coordinates": [-80.12976408045456, 25.94773353463637]}}, {"type": "Feature", "properties": {"cluster": 0, "tweetCount": 110}, "geometry": {"type": "Polygon", "coordinates": [[[-80.146596, 25.95144], [-80.14681, 25.95705], [-80.14565228, 25.96047324], [-80.119783, 25.954437], [-80.11979211, 25.94556092], [-80.12046911, 25.94077811], [-80.121802, 25.933718], [-80.12319638, 25.93431373], [-80.126579, 25.936043], [-80.146596, 25.95144]]]}}, {"type": "Feature", "properties": {"cluster": 1, "clusterCenter": true, "tweetCount": 14}, "geometry": {"type": "Point", "coordinates": [-80.17168377642857, 25.927401680714286]}}, {"type": "Feature", "properties": {"cluster": 1, "tweetCount": 14}, "geometry": {"type": "Polygon", "coordinates": [[[-80.172901, 25.925306], [-80.1750088, 25.92810117], [-80.16917209, 25.92868267], [-80.16965169, 25.92604601], [-80.172901, 25.925306]]]}}, {"type": "Feature", "properties": {"cluster": 2, "clusterCenter": true, "tweetCount": 6}, "geometry": {"type": "Point", "coordinates": [-80.14272871166666, 25.99695108666667]}}, {"type": "Feature", "properties": {"cluster": 2, "tweetCount": 6}, "geometry": {"type": "Polygon", "coordinates": [[[-80.14232683, 25.9912628], [-80.14304644, 25.99975888], [-80.142873, 25.99982142], [-80.142263, 25.99153], [-80.14232683, 25.9912628]]]}}, {"type": "Feature", "properties": {"cluster": 3, "clusterCenter": true, "tweetCount": 8}, "geometry": {"type": "Point", "coordinates": [-80.16566474125, 25.94540906375]}}, {"type": "Feature", "properties": {"cluster": 3, "tweetCount": 8}, "geometry": {"type": "Polygon", "coordinates": [[[-80.16697573, 25.94488846], [-80.16742636, 25.94558428], [-80.167061, 25.94585], [-80.16409803, 25.94641244], [-80.16379281, 25.94507653], [-80.164246, 25.944574], [-80.16697573, 25.94488846]]]}}]}, "tweets": {"type": "FeatureCollection", "features": [{"type": "Feature", "properties": {"tweetID": "903107375351160833", "user": "IslesMarina", "text": "I'm at Don Soffer Exercise Trail in Aventura, FL https://t.co/1CncDZexZu", "date": "2017-08-31T04:09:11.000Z", "speed": "", "timeD": "", "cluster": 0, "dbscan": "core", "dateStr": "2017-08-31T04:09:11.000Z", "timestamp": 1504152551}, "geometry": {"type": "Point", "coordinates": [-80.13839608, 25.95516841]}}, {"type": "Feature", "properties": {"tweetID": "903119819133906945", "user": "IslesMarina", "text": "I'm at Boca Raton Public Library in Boca Raton, FL https://t.co/9O9fm7GNkI", "date": "2017-08-31T04:58:38.000Z", "speed": 32.36523071130765, "timeD": "", "dbscan": "noise", "dateStr": "2017-08-31T04:58:38.000Z", "timestamp": 1504155518, "timeDelta": 2967}, "geometry": {"type": "Point", "coordinates": [-80.11766538, 26.34066076]}}, {"type": "Feature", "properties": {"tweetID": "903120249469456384", "user": "IslesMarina", "text": "I'm at Palmetto Park Plaza in Boca Raton, FL https://t.co/GHDmgNEmG4", "date": "2017-08-31T05:00:21.000Z", "speed": 28.562065679110884, "timeD": "", "dbscan": "noise", "dateStr": "2017-08-31T05:00:21.000Z", "timestamp": 1504155621, "timeDelta": 103}, "geometry": {"type": "Point", "coordinates": [-80.11317725, 26.35177934]}}, {"type": "Feature", "properties": {"tweetID": "903120865646301184", "user": "IslesMarina", "text": "I'm at Boca Raton City Hall in Boca Raton, FL https://t.co/52fzbcafMU", "date": "2017-08-31T05:02:48.000Z", "speed": 34.395258611599715, "timeD": "", "dbscan": "noise", "dateStr": "2017-08-31T05:02:48.000Z", "timestamp": 1504155768, "timeDelta": 147}, "geometry": {"type": "Point", "coordinates": [-80.09050943, 26.35119362]}}, {"type": "Feature", "properties": {"tweetID": "903180432556126208", "user": "IslesMarina", "text": "I'm at Arkham Asylum in Gotham City, FL https://t.co/p4ya1CTFBu", "date": "2017-08-31T08:59:30.000Z", "speed": 6.998390030764766, "timeD": "", "cluster": 0, "dbscan": "core", "dateStr": "2017-08-31T08:59:30.000Z", "timestamp": 1504169970, "timeDelta": 14202}, "geometry": {"type": "Point", "coordinates": [-80.13524481, 25.95375769]}}, {"type": "Feature", "properties": {"tweetID": "903408330139463681", "user": "IslesMarina", "text": "I'm at Fresko in Aventura, FL https://t.co/IRJfGMTUCb", "date": "2017-09-01T00:05:05.000Z", "speed": 0.034713061245936774, "timeD": "", "cluster": 0, "dbscan": "core", "dateStr": "2017-09-01T00:05:05.000Z", "timestamp": 1504224305, "timeDelta": 54335}, "geometry": {"type": "Point", "coordinates": [-80.14329721, 25.95151247]}}, {"type": "Feature", "properties": {"tweetID": "903408784747503616", "user": "IslesMarina", "text": "I'm at Starbucks in Aventura, FL https://t.co/J2vNQw91lH", "date": "2017-09-01T00:06:53.000Z", "speed": 6.468454761461872, "timeD": "", "cluster": 0, "dbscan": "core", "dateStr": "2017-09-01T00:06:53.000Z", "timestamp": 1504224413, "timeDelta": 108}, "geometry": {"type": "Point", "coordinates": [-80.146188, 25.952574]}}, {"type": "Feature", "properties": {"tweetID": "903416028046266372", "user": "IslesMarina", "text": "I'm at BB&amp;T in Aventura, FL https://t.co/jDoS1tlbBa", "date": "2017-09-01T00:35:40.000Z", "speed": 0.16589845070352097, "timeD": "", "cluster": 0, "dbscan": "core", "dateStr": "2017-09-01T00:35:40.000Z", "timestamp": 1504226140, "timeDelta": 1727}, "geometry": {"type": "Point", "coordinates": [-80.14605224, 25.953719]}}, {"type": "Feature", "properties": {"tweetID": "903416289569464320", "user": "IslesMarina", "text": "I'm at @Sears in Miami, FL https://t.co/1w5nruNZRG", "date": "2017-09-01T00:36:42.000Z", "speed": 13.64451037511906, "timeD": "", "cluster": 0, "dbscan": "core", "dateStr": "2017-09-01T00:36:42.000Z", "timestamp": 1504226202, "timeDelta": 62}, "geometry": {"type": "Point", "coordinates": [-80.14681, 25.95705]}}, {"type": "Feature", "properties": {"tweetID": "903475261882023936", "user": "IslesMarina", "text": "I'm at Aventura Marina Resort &amp; Spa in Aventura, FL https://t.co/gYqiuVkxlu", "date": "2017-09-01T04:31:02.000Z", "speed": 0.21685190389930398, "timeD": "", "cluster": 0, "dbscan": "core", "dateStr": "2017-09-01T04:31:02.000Z", "timestamp": 1504240262, "timeDelta": 14060}, "geometry": {"type": "Point", "coordinates": [-80.13456329, 25.95167381]}}, {"type": "Feature", "properties": {"tweetID": "903475389397327875", "user": "IslesMarina", "text": "I'm at Brooklyn Water Bagel  Co in Hollywood, FL https://t.co/z2z9uFw2yj", "date": "2017-09-01T04:31:33.000Z", "speed": 33.861564331762196, "timeD": "", "cluster": 0, "dbscan": "core", "dateStr": "2017-09-01T04:31:33.000Z", "timestamp": 1504240293, "timeDelta": 31}, "geometry": {"type": "Point", "coordinates": [-80.13896853, 25.95312608]}}, {"type": "Feature", "properties": {"tweetID": "903650055378358272", "user": "IslesMarina", "text": "The City of Excellence! Miami \ud83c\udf34 Sunny Isles Beach \ud83c\udf1e Golden Beach \ud83c\udf0f Aventura (@ Aventura, FL in FL) https://t.co/EoT7nITp02", "date": "2017-09-01T16:05:36.000Z", "speed": 0.020956675378378208, "timeD": "", "cluster": 0, "dbscan": "core", "dateStr": "2017-09-01T16:05:36.000Z", "timestamp": 1504281936, "timeDelta": 41643}, "geometry": {"type": "Point", "coordinates": [-80.13921261, 25.95662664]}}, {"type": "Feature", "properties": {"tweetID": "903652181697540096", "user": "IslesMarina", "text": "I'm at Aventura Parc Central in Aventura, FL https://t.co/yAQcOwZaXN", "date": "2017-09-01T16:14:03.000Z", "speed": 2.090261238336899, "timeD": "", "cluster": 0, "dbscan": "core", "dateStr": "2017-09-01T16:14:03.000Z", "timestamp": 1504282443, "timeDelta": 507}, "geometry": {"type": "Point", "coordinates": [-80.135704, 25.953765]}}, {"type": "Feature", "properties": {"tweetID": "903652266024062976", "user": "IslesMarina", "text": "I'm at Parc Central East in Aventura, FL https://t.co/sN24r0izAI", "date": "2017-09-01T16:14:23.000Z", "speed": 21.68912717297179, "timeD": "", "cluster": 0, "dbscan": "core", "dateStr": "2017-09-01T16:14:23.000Z", "timestamp": 1504282463, "timeDelta": 20}, "geometry": {"type": "Point", "coordinates": [-80.13386541, 25.95431863]}}, {"type": "Feature", "properties": {"tweetID": "903652313084125185", "user": "IslesMarina", "text": "I'm at Jenny's Gourmet Shop in Aventura, FL https://t.co/dyEcIzxRbF", "date": "2017-09-01T16:14:35.000Z", "speed": 15.168110337330837, "timeD": "", "cluster": 0, "dbscan": "core", "dateStr": "2017-09-01T16:14:35.000Z", "timestamp": 1504282475, "timeDelta": 12}, "geometry": {"type": "Point", "coordinates": [-80.133992, 25.953596]}}, {"type": "Feature", "properties": {"tweetID": "903670052842561536", "user": "IslesMarina", "text": "I'm at @Publix in Aventura, FL https://t.co/qcMHV1kPsN", "date": "2017-09-01T17:25:04.000Z", "speed": 0.6787367592182937, "timeD": "", "cluster": 0, "dbscan": "core", "dateStr": "2017-09-01T17:25:04.000Z", "timestamp": 1504286704, "timeDelta": 4229}, "geometry": {"type": "Point", "coordinates": [-80.146596, 25.95144]}}, {"type": "Feature", "properties": {"tweetID": "903670138699960324", "user": "IslesMarina", "text": "I'm at @BedBathBeyond in Aventura, FL https://t.co/n6zxiQXHdz", "date": "2017-09-01T17:25:25.000Z", "speed": 21.879405595441632, "timeD": "", "cluster": 0, "dbscan": "core", "dateStr": "2017-09-01T17:25:25.000Z", "timestamp": 1504286725, "timeDelta": 21}, "geometry": {"type": "Point", "coordinates": [-80.14543422, 25.95296276]}}, {"type": "Feature", "properties": {"tweetID": "903678061857660928", "user": "IslesMarina", "text": "I'm at @Walmart Supercenter in North Miami Beach, FL https://t.co/99I3XBGlri", "date": "2017-09-01T17:56:54.000Z", "speed": 4.482908407316915, "timeD": "", "cluster": 1, "dbscan": "core", "dateStr": "2017-09-01T17:56:54.000Z", "timestamp": 1504288614, "timeDelta": 1889}, "geometry": {"type": "Point", "coordinates": [-80.1711722, 25.92800982]}}, {"type": "Feature", "properties": {"tweetID": "903709961456365568", "user": "IslesMarina", "text": "I'm at The @HomeDepot in North Miami Beach, FL https://t.co/vIEeqmnFTw https://t.co/n7Bkxch4jF", "date": "2017-09-01T20:03:39.000Z", "speed": 0.11292763884790723, "timeD": "", "cluster": 1, "dbscan": "core", "dateStr": "2017-09-01T20:03:39.000Z", "timestamp": 1504296219, "timeDelta": 7605}, "geometry": {"type": "Point", "coordinates": [-80.1750088, 25.92810117]}}, {"type": "Feature", "properties": {"tweetID": "903716898973601792", "user": "IslesMarina", "text": "I'm at 163rd Street Mall in Miami, FL https://t.co/9XkbfmcoKH", "date": "2017-09-01T20:31:13.000Z", "speed": 0.3149082997624213, "timeD": "", "cluster": 1, "dbscan": "core", "dateStr": "2017-09-01T20:31:13.000Z", "timestamp": 1504297873, "timeDelta": 1654}, "geometry": {"type": "Point", "coordinates": [-80.17331396, 25.92666631]}}, {"type": "Feature", "properties": {"tweetID": "903717000383475712", "user": "IslesMarina", "text": "I'm at @Walmart Supercenter in North Miami Beach, FL https://t.co/zYYrGIBWRV", "date": "2017-09-01T20:31:37.000Z", "speed": 24.347005374041224, "timeD": "", "cluster": 1, "dbscan": "core", "dateStr": "2017-09-01T20:31:37.000Z", "timestamp": 1504297897, "timeDelta": 24}, "geometry": {"type": "Point", "coordinates": [-80.1711722, 25.92800982]}}, {"type": "Feature", "properties": {"tweetID": "903742734682521601", "user": "IslesMarina", "text": "I'm at Coco's Salon in Aventura, FL https://t.co/jNtKcQwnFO", "date": "2017-09-01T22:13:53.000Z", "speed": 1.556359185987982, "timeD": "", "cluster": 0, "dbscan": "core", "dateStr": "2017-09-01T22:13:53.000Z", "timestamp": 1504304033, "timeDelta": 6136}, "geometry": {"type": "Point", "coordinates": [-80.14157449, 25.95566389]}}, {"type": "Feature", "properties": {"tweetID": "903743580598132736", "user": "IslesMarina", "text": "I'm at Arkham Asylum in Gotham City, FL https://t.co/SI4U7MstqK", "date": "2017-09-01T22:17:15.000Z", "speed": 7.392997959692573, "timeD": "", "cluster": 0, "dbscan": "core", "dateStr": "2017-09-01T22:17:15.000Z", "timestamp": 1504304235, "timeDelta": 202}, "geometry": {"type": "Point", "coordinates": [-80.13524481, 25.95375769]}}, {"type": "Feature", "properties": {"tweetID": "903777625688215552", "user": "IslesMarina", "text": "I'm at McDonald's in North Miami, FL https://t.co/sbp9pNUoJ7", "date": "2017-09-02T00:32:31.000Z", "speed": 2.4045215857338174, "timeD": "", "dbscan": "noise", "dateStr": "2017-09-02T00:32:31.000Z", "timestamp": 1504312351, "timeDelta": 8116}, "geometry": {"type": "Point", "coordinates": [-80.18608165, 25.89003071]}}, {"type": "Feature", "properties": {"tweetID": "903781212405325824", "user": "IslesMarina", "text": "I'm at Family Dollar in Miami, FL https://t.co/0GkY0NUpYN", "date": "2017-09-02T00:46:47.000Z", "speed": 10.901186169328433, "timeD": "", "dbscan": "noise", "dateStr": "2017-09-02T00:46:47.000Z", "timestamp": 1504313207, "timeDelta": 856}, "geometry": {"type": "Point", "coordinates": [-80.22670973, 25.88163484]}}, {"type": "Feature", "properties": {"tweetID": "904024714074521600", "user": "IslesMarina", "text": "I'm at Jenny's Gourmet Shop in Aventura, FL https://t.co/hciwCzMjGn", "date": "2017-09-02T16:54:22.000Z", "speed": 0.472078733201262, "timeD": "", "cluster": 0, "dbscan": "core", "dateStr": "2017-09-02T16:54:22.000Z", "timestamp": 1504371262, "timeDelta": 58055}, "geometry": {"type": "Point", "coordinates": [-80.133992, 25.953596]}}, {"type": "Feature", "properties": {"tweetID": "904024977200074754", "user": "IslesMarina", "text": "I'm at Don Soffer Exercise Trail in Aventura, FL https://t.co/Wq3MwMnpM4", "date": "2017-09-02T16:55:25.000Z", "speed": 16.827196446832186, "timeD": "", "cluster": 0, "dbscan": "core", "dateStr": "2017-09-02T16:55:25.000Z", "timestamp": 1504371325, "timeDelta": 63}, "geometry": {"type": "Point", "coordinates": [-80.13839608, 25.95516841]}}, {"type": "Feature", "properties": {"tweetID": "904025028227997697", "user": "IslesMarina", "text": "I'm at Mystic Pointe Tower in Aventura, FL https://t.co/tZRoXcjZje", "date": "2017-09-02T16:55:37.000Z", "speed": 199.9798160702544, "timeD": "", "cluster": 0, "dbscan": "core", "dateStr": "2017-09-02T16:55:37.000Z", "timestamp": 1504371337, "timeDelta": 12}, "geometry": {"type": "Point", "coordinates": [-80.12789504, 25.95320083]}}, {"type": "Feature", "properties": {"tweetID": "904028062886629378", "user": "IslesMarina", "text": "I'm at Ramada Plaza @MarcoPoloBeach Resort in North Miami Beach, FL https://t.co/MwhXUhfqcl", "date": "2017-09-02T17:07:40.000Z", "speed": 2.545932446181361, "timeD": "", "cluster": 0, "dbscan": "core", "dateStr": "2017-09-02T17:07:40.000Z", "timestamp": 1504372060, "timeDelta": 723}, "geometry": {"type": "Point", "coordinates": [-80.119783, 25.954437]}}, {"type": "Feature", "properties": {"tweetID": "904054896676233216", "user": "IslesMarina", "text": "Saturday Blessings To All \ud83d\ude4f\ud83c\udffc Keep The Hope and Have Faith! (@ New Hope Baptist Church) https://t.co/8uXDvzfzmn https://t.co/uc7wuYmsRH", "date": "2017-09-02T18:54:18.000Z", "speed": 5.0872944340785535, "timeD": "", "dbscan": "noise", "dateStr": "2017-09-02T18:54:18.000Z", "timestamp": 1504378458, "timeDelta": 6398}, "geometry": {"type": "Point", "coordinates": [-80.22934025, 25.86840432]}}, {"type": "Feature", "properties": {"tweetID": "904055147277545473", "user": "IslesMarina", "text": "I'm at Goodway Coffee Shop in Miami, FL https://t.co/QeEXiCrlzU", "date": "2017-09-02T18:55:18.000Z", "speed": 78.94537587002202, "timeD": "", "dbscan": "noise", "dateStr": "2017-09-02T18:55:18.000Z", "timestamp": 1504378518, "timeDelta": 60}, "geometry": {"type": "Point", "coordinates": [-80.210901, 25.87774]}}, {"type": "Feature", "properties": {"tweetID": "904055880202817536", "user": "IslesMarina", "text": "I'm at Central  Tag Agency in Miami, FL https://t.co/AW84KmgHuB", "date": "2017-09-02T18:58:13.000Z", "speed": 40.53333698309791, "timeD": "", "dbscan": "noise", "dateStr": "2017-09-02T18:58:13.000Z", "timestamp": 1504378693, "timeDelta": 175}, "geometry": {"type": "Point", "coordinates": [-80.24245349, 25.87513125]}}, {"type": "Feature", "properties": {"tweetID": "904056324933214209", "user": "IslesMarina", "text": "Blessings For The New Month of September!! \ud83d\ude4f\ud83c\udffc Cheers and Blessings! https://t.co/K4w3xwaqub", "date": "2017-09-02T18:59:59.000Z", "speed": 43.575831811311076, "timeD": "", "dbscan": "noise", "dateStr": "2017-09-02T18:59:59.000Z", "timestamp": 1504378799, "timeDelta": 106}, "geometry": {"type": "Point", "coordinates": [-80.223169, 25.868532]}}, {"type": "Feature", "properties": {"tweetID": "904111112400101376", "user": "IslesMarina", "text": "I'm at Aventura Parc Central in Aventura, FL https://t.co/rIp03JlYDo", "date": "2017-09-02T22:37:41.000Z", "speed": 2.2094856731456844, "timeD": "", "cluster": 0, "dbscan": "core", "dateStr": "2017-09-02T22:37:41.000Z", "timestamp": 1504391861, "timeDelta": 13062}, "geometry": {"type": "Point", "coordinates": [-80.135704, 25.953765]}}, {"type": "Feature", "properties": {"tweetID": "904122816601182208", "user": "IslesMarina", "text": "I'm at @Walmart Supercenter in North Miami Beach, FL https://t.co/qhbfoBarDh", "date": "2017-09-02T23:24:11.000Z", "speed": 3.6559699107424906, "timeD": "", "cluster": 1, "dbscan": "core", "dateStr": "2017-09-02T23:24:11.000Z", "timestamp": 1504394651, "timeDelta": 2790}, "geometry": {"type": "Point", "coordinates": [-80.1711722, 25.92800982]}}, {"type": "Feature", "properties": {"tweetID": "904123805228036097", "user": "IslesMarina", "text": "I'm at The @HomeDepot in North Miami Beach, FL https://t.co/oQUbts6VBB", "date": "2017-09-02T23:28:07.000Z", "speed": 3.639045311179383, "timeD": "", "cluster": 1, "dbscan": "core", "dateStr": "2017-09-02T23:28:07.000Z", "timestamp": 1504394887, "timeDelta": 236}, "geometry": {"type": "Point", "coordinates": [-80.1750088, 25.92810117]}}, {"type": "Feature", "properties": {"tweetID": "904128722990714884", "user": "IslesMarina", "text": "I'm at @Walgreens in North Miami Beach, FL https://t.co/XH1EK1SgUN", "date": "2017-09-02T23:47:40.000Z", "speed": 1.1110612646014688, "timeD": "", "cluster": 1, "dbscan": "core", "dateStr": "2017-09-02T23:47:40.000Z", "timestamp": 1504396060, "timeDelta": 1173}, "geometry": {"type": "Point", "coordinates": [-80.16965169, 25.92604601]}}, {"type": "Feature", "properties": {"tweetID": "904137935481602049", "user": "IslesMarina", "text": "I'm at Aventura Circle in Aventura, FL https://t.co/LMJvB5yjyp", "date": "2017-09-03T00:24:16.000Z", "speed": 4.491258156357285, "timeD": "", "cluster": 0, "dbscan": "core", "dateStr": "2017-09-03T00:24:16.000Z", "timestamp": 1504398256, "timeDelta": 2196}, "geometry": {"type": "Point", "coordinates": [-80.1385978, 25.95417871]}}, {"type": "Feature", "properties": {"tweetID": "904138121616515072", "user": "IslesMarina", "text": "I'm at Brooklyn Water Bagel  Co in Hollywood, FL https://t.co/BNCWw9urA2", "date": "2017-09-03T00:25:00.000Z", "speed": 6.2438188397768135, "timeD": "", "cluster": 0, "dbscan": "core", "dateStr": "2017-09-03T00:25:00.000Z", "timestamp": 1504398300, "timeDelta": 44}, "geometry": {"type": "Point", "coordinates": [-80.13896853, 25.95312608]}}, {"type": "Feature", "properties": {"tweetID": "904138524986941442", "user": "IslesMarina", "text": "I'm at City of Aventura Government Center in Aventura, FL https://t.co/DoTDHW8Go0", "date": "2017-09-03T00:26:37.000Z", "speed": 1.5831445129924273, "timeD": "", "cluster": 0, "dbscan": "core", "dateStr": "2017-09-03T00:26:37.000Z", "timestamp": 1504398397, "timeDelta": 97}, "geometry": {"type": "Point", "coordinates": [-80.13931745, 25.95259458]}}, {"type": "Feature", "properties": {"tweetID": "904138597623885824", "user": "IslesMarina", "text": "I'm at Mystic Pointe Tower 600 GYM in \u041c\u0430\u0439\u0430\u043c\u0438, FL https://t.co/NZZBgPg4J2", "date": "2017-09-03T00:26:54.000Z", "speed": 95.31458840293385, "timeD": "", "cluster": 0, "dbscan": "core", "dateStr": "2017-09-03T00:26:54.000Z", "timestamp": 1504398414, "timeDelta": 17}, "geometry": {"type": "Point", "coordinates": [-80.13208252, 25.95289552]}}, {"type": "Feature", "properties": {"tweetID": "904138742532845569", "user": "IslesMarina", "text": "I'm at Principal Pool @ Parc Central Aventura in Aventura, FL https://t.co/OlWNspmYxx", "date": "2017-09-03T00:27:28.000Z", "speed": 22.677569229128995, "timeD": "", "cluster": 0, "dbscan": "core", "dateStr": "2017-09-03T00:27:28.000Z", "timestamp": 1504398448, "timeDelta": 34}, "geometry": {"type": "Point", "coordinates": [-80.13544109, 25.95359071]}}, {"type": "Feature", "properties": {"tweetID": "904138929217077254", "user": "IslesMarina", "text": "I'm at Car Wash at Mobil in Aventura, FL https://t.co/xILkpqhF0I", "date": "2017-09-03T00:28:13.000Z", "speed": 6.056397280043768, "timeD": "", "cluster": 0, "dbscan": "core", "dateStr": "2017-09-03T00:28:13.000Z", "timestamp": 1504398493, "timeDelta": 45}, "geometry": {"type": "Point", "coordinates": [-80.13425797, 25.95332973]}}, {"type": "Feature", "properties": {"tweetID": "904172282628771840", "user": "IslesMarina", "text": "I'm at Aventura Marina Resort &amp; Spa in Aventura, FL https://t.co/2gL54YVUk2", "date": "2017-09-03T02:40:45.000Z", "speed": 0.05252014020751192, "timeD": "", "cluster": 0, "dbscan": "core", "dateStr": "2017-09-03T02:40:45.000Z", "timestamp": 1504406445, "timeDelta": 7952}, "geometry": {"type": "Point", "coordinates": [-80.13456329, 25.95167381]}}, {"type": "Feature", "properties": {"tweetID": "904172638100226048", "user": "IslesMarina", "text": "I'm at Car Wash at Mobil in Aventura, FL https://t.co/cP698tLzwQ", "date": "2017-09-03T02:42:10.000Z", "speed": 4.913413587413349, "timeD": "", "cluster": 0, "dbscan": "core", "dateStr": "2017-09-03T02:42:10.000Z", "timestamp": 1504406530, "timeDelta": 85}, "geometry": {"type": "Point", "coordinates": [-80.13425797, 25.95332973]}}, {"type": "Feature", "properties": {"tweetID": "904177996583591936", "user": "IslesMarina", "text": "I'm at Aventura Marina One Condominium in Aventura, FL https://t.co/RLt776IYEK", "date": "2017-09-03T03:03:27.000Z", "speed": 0.40036829445062433, "timeD": "", "cluster": 0, "dbscan": "core", "dateStr": "2017-09-03T03:03:27.000Z", "timestamp": 1504407807, "timeDelta": 1277}, "geometry": {"type": "Point", "coordinates": [-80.13564827, 25.95169891]}}, {"type": "Feature", "properties": {"tweetID": "904178135306039298", "user": "IslesMarina", "text": "I'm at Country Club Drive And Yacht Club Way in Miami, FL https://t.co/vMDMzcA12Z", "date": "2017-09-03T03:04:00.000Z", "speed": 39.94006023533681, "timeD": "", "cluster": 0, "dbscan": "core", "dateStr": "2017-09-03T03:04:00.000Z", "timestamp": 1504407840, "timeDelta": 33}, "geometry": {"type": "Point", "coordinates": [-80.13032141, 25.95396155]}}, {"type": "Feature", "properties": {"tweetID": "904178434959704064", "user": "IslesMarina", "text": "I'm at Aventura Marina Resort &amp; Spa in Aventura, FL https://t.co/rXKci5WMAu", "date": "2017-09-03T03:05:12.000Z", "speed": 15.369808768974533, "timeD": "", "cluster": 0, "dbscan": "core", "dateStr": "2017-09-03T03:05:12.000Z", "timestamp": 1504407912, "timeDelta": 72}, "geometry": {"type": "Point", "coordinates": [-80.13456329, 25.95167381]}}, {"type": "Feature", "properties": {"tweetID": "904178963253264386", "user": "IslesMarina", "text": "I'm at Parc Central South Pool in Aventura, FL https://t.co/ybT5RaCLzE", "date": "2017-09-03T03:07:18.000Z", "speed": 4.737608183756054, "timeD": "", "cluster": 0, "dbscan": "core", "dateStr": "2017-09-03T03:07:18.000Z", "timestamp": 1504408038, "timeDelta": 126}, "geometry": {"type": "Point", "coordinates": [-80.13373456, 25.95395429]}}, {"type": "Feature", "properties": {"tweetID": "904179250424668160", "user": "IslesMarina", "text": "I'm at Founder's Park Tennis Courts in Aventura, FL https://t.co/72gk7ysEVI", "date": "2017-09-03T03:08:26.000Z", "speed": 19.55862789444041, "timeD": "", "cluster": 0, "dbscan": "core", "dateStr": "2017-09-03T03:08:26.000Z", "timestamp": 1504408106, "timeDelta": 68}, "geometry": {"type": "Point", "coordinates": [-80.139466, 25.952535]}}, {"type": "Feature", "properties": {"tweetID": "904179489432854528", "user": "IslesMarina", "text": "I'm at Brooklyn Water Bagel  Co in Hollywood, FL https://t.co/tBpCPGEccm", "date": "2017-09-03T03:09:23.000Z", "speed": 3.23568536764743, "timeD": "", "cluster": 0, "dbscan": "core", "dateStr": "2017-09-03T03:09:23.000Z", "timestamp": 1504408163, "timeDelta": 57}, "geometry": {"type": "Point", "coordinates": [-80.13896853, 25.95312608]}}, {"type": "Feature", "properties": {"tweetID": "904211125297975300", "user": "IslesMarina", "text": "I'm at Founders Park in Aventura, FL https://t.co/9U1inOpXZO", "date": "2017-09-03T05:15:06.000Z", "speed": 0.04803198359295909, "timeD": "", "cluster": 0, "dbscan": "core", "dateStr": "2017-09-03T05:15:06.000Z", "timestamp": 1504415706, "timeDelta": 7543}, "geometry": {"type": "Point", "coordinates": [-80.13805261, 25.95192522]}}, {"type": "Feature", "properties": {"tweetID": "904211909519581188", "user": "IslesMarina", "text": "I'm at Camden Balcony in Miami, FL https://t.co/WublEWIvBi", "date": "2017-09-03T05:18:13.000Z", "speed": 3.196113227281648, "timeD": "", "cluster": 0, "dbscan": "core", "dateStr": "2017-09-03T05:18:13.000Z", "timestamp": 1504415893, "timeDelta": 187}, "geometry": {"type": "Point", "coordinates": [-80.13770913, 25.95430737]}}, {"type": "Feature", "properties": {"tweetID": "904215278392938496", "user": "IslesMarina", "text": "I'm at Artech in Aventura, FL https://t.co/00Rk0OTqzf", "date": "2017-09-03T05:31:36.000Z", "speed": 1.7307161351783735, "timeD": "", "cluster": 0, "dbscan": "core", "dateStr": "2017-09-03T05:31:36.000Z", "timestamp": 1504416696, "timeDelta": 803}, "geometry": {"type": "Point", "coordinates": [-80.13207162, 25.95665362]}}, {"type": "Feature", "properties": {"tweetID": "904253413260713984", "user": "IslesMarina", "text": "I'm at Plenty Poke in Miami Beach, FL https://t.co/4FHRvolZaO", "date": "2017-09-03T08:03:08.000Z", "speed": 4.8693219342099505, "timeD": "", "dbscan": "noise", "dateStr": "2017-09-03T08:03:08.000Z", "timestamp": 1504425788, "timeDelta": 9092}, "geometry": {"type": "Point", "coordinates": [-80.133379, 25.778726]}}, {"type": "Feature", "properties": {"tweetID": "904403533948178432", "user": "IslesMarina", "text": "I'm at Chase Bank - @chasesupport in Miami Beach, FL https://t.co/CwM5uXLBwD", "date": "2017-09-03T17:59:40.000Z", "speed": 0.5333697537859197, "timeD": "", "dbscan": "noise", "dateStr": "2017-09-03T17:59:40.000Z", "timestamp": 1504461580, "timeDelta": 35792}, "geometry": {"type": "Point", "coordinates": [-80.120665, 25.854593]}}, {"type": "Feature", "properties": {"tweetID": "904440949799047178", "user": "IslesMarina", "text": "I'm at Amscot in Miami Gardens, Florida https://t.co/XOMzREcbCl", "date": "2017-09-03T20:28:20.000Z", "speed": 3.3780199503915274, "timeD": "", "dbscan": "noise", "dateStr": "2017-09-03T20:28:20.000Z", "timestamp": 1504470500, "timeDelta": 8920}, "geometry": {"type": "Point", "coordinates": [-80.21351, 25.942286]}}, {"type": "Feature", "properties": {"tweetID": "904446862643654656", "user": "IslesMarina", "text": "I'm at @Walmart Supercenter in North Miami Beach, FL https://t.co/RR7JQwLl71", "date": "2017-09-03T20:51:50.000Z", "speed": 7.175455163382776, "timeD": "", "cluster": 1, "dbscan": "core", "dateStr": "2017-09-03T20:51:50.000Z", "timestamp": 1504471910, "timeDelta": 1410}, "geometry": {"type": "Point", "coordinates": [-80.1711722, 25.92800982]}}, {"type": "Feature", "properties": {"tweetID": "904447433618403328", "user": "IslesMarina", "text": "McDonald\u2019s or The North Miami Beach @Walmart Super Center (at @McDonalds in North Miami Beach, FL) https://t.co/RVjCcQiHKk", "date": "2017-09-03T20:54:06.000Z", "speed": 0.15370248332584863, "timeD": "", "cluster": 1, "dbscan": "core", "dateStr": "2017-09-03T20:54:06.000Z", "timestamp": 1504472046, "timeDelta": 136}, "geometry": {"type": "Point", "coordinates": [-80.17123215, 25.92794539]}}, {"type": "Feature", "properties": {"tweetID": "904447693069717509", "user": "IslesMarina", "text": "I'm at Jiffy Foods Market &amp; Deli in North Miami Beach, FL https://t.co/1IWxMYZCPG", "date": "2017-09-03T20:55:08.000Z", "speed": 5.000996953588488, "timeD": "", "cluster": 1, "dbscan": "core", "dateStr": "2017-09-03T20:55:08.000Z", "timestamp": 1504472108, "timeDelta": 62}, "geometry": {"type": "Point", "coordinates": [-80.17001683, 25.92734683]}}, {"type": "Feature", "properties": {"tweetID": "904448153679794176", "user": "IslesMarina", "text": "I'm at Mishcon Field in north miam beach, FL https://t.co/mSzCOW1Brw", "date": "2017-09-03T20:56:58.000Z", "speed": 3.4760688065763006, "timeD": "", "cluster": 1, "dbscan": "core", "dateStr": "2017-09-03T20:56:58.000Z", "timestamp": 1504472218, "timeDelta": 110}, "geometry": {"type": "Point", "coordinates": [-80.16917209, 25.92868267]}}, {"type": "Feature", "properties": {"tweetID": "904448322295005184", "user": "IslesMarina", "text": "I'm at @SUBWAY in North Miami Beach, FL https://t.co/zezE2AFrHS", "date": "2017-09-03T20:57:38.000Z", "speed": 21.29964048193498, "timeD": "", "cluster": 1, "dbscan": "core", "dateStr": "2017-09-03T20:57:38.000Z", "timestamp": 1504472258, "timeDelta": 40}, "geometry": {"type": "Point", "coordinates": [-80.17149919, 25.92597252]}}, {"type": "Feature", "properties": {"tweetID": "904448488070664192", "user": "IslesMarina", "text": "I'm at Colombia's Grill Restaurant in North Miami Beach, FL https://t.co/d4tiqQj7Hl", "date": "2017-09-03T20:58:18.000Z", "speed": 8.870715947968222, "timeD": "", "cluster": 1, "dbscan": "core", "dateStr": "2017-09-03T20:58:18.000Z", "timestamp": 1504472298, "timeDelta": 40}, "geometry": {"type": "Point", "coordinates": [-80.172901, 25.925306]}}, {"type": "Feature", "properties": {"tweetID": "904456848593563648", "user": "IslesMarina", "text": "I'm at Holistic Centre in Miami, FL https://t.co/e5f8y4uPyj", "date": "2017-09-03T21:31:31.000Z", "speed": 0.33350675526003987, "timeD": "", "cluster": 1, "dbscan": "core", "dateStr": "2017-09-03T21:31:31.000Z", "timestamp": 1504474291, "timeDelta": 1993}, "geometry": {"type": "Point", "coordinates": [-80.17107956, 25.92741618]}}, {"type": "Feature", "properties": {"tweetID": "904485200058617857", "user": "IslesMarina", "text": "I'm at Aventura Circle in Aventura, FL https://t.co/cmNQdTcrro", "date": "2017-09-03T23:24:10.000Z", "speed": 1.4583445224378946, "timeD": "", "cluster": 0, "dbscan": "core", "dateStr": "2017-09-03T23:24:10.000Z", "timestamp": 1504481050, "timeDelta": 6759}, "geometry": {"type": "Point", "coordinates": [-80.1385978, 25.95417871]}}, {"type": "Feature", "properties": {"tweetID": "904485384943493122", "user": "IslesMarina", "text": "I'm at Parc Central Aventura - @parcentralcondo in Aventura, FL https://t.co/n1Ss1Gureg", "date": "2017-09-03T23:24:54.000Z", "speed": 25.849297136390042, "timeD": "", "cluster": 0, "dbscan": "core", "dateStr": "2017-09-03T23:24:54.000Z", "timestamp": 1504481094, "timeDelta": 44}, "geometry": {"type": "Point", "coordinates": [-80.14322519, 25.9522856]}}, {"type": "Feature", "properties": {"tweetID": "904505665191804930", "user": "IslesMarina", "text": "I'm at Parc Central South Pool in Aventura, FL https://t.co/zClFeUK6Lc", "date": "2017-09-04T00:45:30.000Z", "speed": 0.44736867804915453, "timeD": "", "cluster": 0, "dbscan": "core", "dateStr": "2017-09-04T00:45:30.000Z", "timestamp": 1504485930, "timeDelta": 4836}, "geometry": {"type": "Point", "coordinates": [-80.13373456, 25.95395429]}}, {"type": "Feature", "properties": {"tweetID": "904765964239204354", "user": "IslesMarina", "text": "I'm at Aventura Parc Central in Aventura, FL https://t.co/40SSsttpw2", "date": "2017-09-04T17:59:50.000Z", "speed": 0.007140091328862433, "timeD": "", "cluster": 0, "dbscan": "core", "dateStr": "2017-09-04T17:59:50.000Z", "timestamp": 1504547990, "timeDelta": 62060}, "geometry": {"type": "Point", "coordinates": [-80.135704, 25.953765]}}, {"type": "Feature", "properties": {"tweetID": "904766071873441794", "user": "IslesMarina", "text": "I'm at Jenny's Gourmet Shop in Aventura, FL https://t.co/x6mPkeHkiL", "date": "2017-09-04T18:00:15.000Z", "speed": 15.412451940406434, "timeD": "", "cluster": 0, "dbscan": "core", "dateStr": "2017-09-04T18:00:15.000Z", "timestamp": 1504548015, "timeDelta": 25}, "geometry": {"type": "Point", "coordinates": [-80.133992, 25.953596]}}, {"type": "Feature", "properties": {"tweetID": "904766138625732608", "user": "IslesMarina", "text": "I'm at Don Soffer Exercise Trail in Aventura, FL https://t.co/GQlKyVH7sh", "date": "2017-09-04T18:00:31.000Z", "speed": 66.25708600940173, "timeD": "", "cluster": 0, "dbscan": "core", "dateStr": "2017-09-04T18:00:31.000Z", "timestamp": 1504548031, "timeDelta": 16}, "geometry": {"type": "Point", "coordinates": [-80.13839608, 25.95516841]}}, {"type": "Feature", "properties": {"tweetID": "904766220708274176", "user": "IslesMarina", "text": "I'm at Aventura Marina Resort &amp; Spa in Aventura, FL https://t.co/TdPhQuvtES", "date": "2017-09-04T18:00:51.000Z", "speed": 61.05953332502297, "timeD": "", "cluster": 0, "dbscan": "core", "dateStr": "2017-09-04T18:00:51.000Z", "timestamp": 1504548051, "timeDelta": 20}, "geometry": {"type": "Point", "coordinates": [-80.13456329, 25.95167381]}}, {"type": "Feature", "properties": {"tweetID": "904794281797439488", "user": "IslesMarina", "text": "I'm at World Market &amp; Cafe in Hollywood, FL https://t.co/I9XivCj5X7", "date": "2017-09-04T19:52:21.000Z", "speed": 1.8121286633644038, "timeD": "", "cluster": 2, "dbscan": "core", "dateStr": "2017-09-04T19:52:21.000Z", "timestamp": 1504554741, "timeDelta": 6690}, "geometry": {"type": "Point", "coordinates": [-80.142873, 25.99982142]}}, {"type": "Feature", "properties": {"tweetID": "904819369418657792", "user": "IslesMarina", "text": "I'm at City of Hollywood - @cohgov in FL https://t.co/BtF47Pipbk", "date": "2017-09-04T21:32:03.000Z", "speed": 0.5790899315528568, "timeD": "", "dbscan": "noise", "dateStr": "2017-09-04T21:32:03.000Z", "timestamp": 1504560723, "timeDelta": 5982}, "geometry": {"type": "Point", "coordinates": [-80.14844883, 26.01281078]}}, {"type": "Feature", "properties": {"tweetID": "904819453669539841", "user": "IslesMarina", "text": "I'm at Wonderland Mantesory Academy in \u0413\u043e\u043b\u043b\u0438\u0432\u0443\u0434, FL https://t.co/uGmZmLLvSj", "date": "2017-09-04T21:32:23.000Z", "speed": 273.6338187528472, "timeD": "", "cluster": 2, "dbscan": "core", "dateStr": "2017-09-04T21:32:23.000Z", "timestamp": 1504560743, "timeDelta": 20}, "geometry": {"type": "Point", "coordinates": [-80.142263, 25.99153]}}, {"type": "Feature", "properties": {"tweetID": "904819549480132608", "user": "IslesMarina", "text": "I'm at El Rancho Motel in Hallandale Beach, FL https://t.co/kCsLS0L4ct", "date": "2017-09-04T21:32:45.000Z", "speed": 3.090841585150781, "timeD": "", "cluster": 2, "dbscan": "core", "dateStr": "2017-09-04T21:32:45.000Z", "timestamp": 1504560765, "timeDelta": 22}, "geometry": {"type": "Point", "coordinates": [-80.14232683, 25.9912628]}}, {"type": "Feature", "properties": {"tweetID": "904833668216225792", "user": "IslesMarina", "text": "I'm at Miami-Dade Transit Office in Aventura, FL https://t.co/W9b7PvjrZA", "date": "2017-09-04T22:28:52.000Z", "speed": 2.4354883386588098, "timeD": "", "cluster": 0, "dbscan": "core", "dateStr": "2017-09-04T22:28:52.000Z", "timestamp": 1504564132, "timeDelta": 3367}, "geometry": {"type": "Point", "coordinates": [-80.144399, 25.958358]}}, {"type": "Feature", "properties": {"tweetID": "904833926547611648", "user": "IslesMarina", "text": "I'm at @AventuraMall in Aventura, FL https://t.co/WjrRYZhHJY", "date": "2017-09-04T22:29:53.000Z", "speed": 12.673608563276423, "timeD": "", "cluster": 0, "dbscan": "core", "dateStr": "2017-09-04T22:29:53.000Z", "timestamp": 1504564193, "timeDelta": 61}, "geometry": {"type": "Point", "coordinates": [-80.1467181, 25.95605448]}}, {"type": "Feature", "properties": {"tweetID": "904920033020846082", "user": "IslesMarina", "text": "I'm at Founders Park in Aventura, FL https://t.co/6Ocya4CbuS", "date": "2017-09-05T04:12:03.000Z", "speed": 0.10687129207982454, "timeD": "", "cluster": 0, "dbscan": "core", "dateStr": "2017-09-05T04:12:03.000Z", "timestamp": 1504584723, "timeDelta": 20530}, "geometry": {"type": "Point", "coordinates": [-80.13805261, 25.95192522]}}, {"type": "Feature", "properties": {"tweetID": "904923701161943042", "user": "IslesMarina", "text": "I'm at Hollywoof Dog Park in Hollywood, FL https://t.co/Sll7YMRmcs", "date": "2017-09-05T04:26:37.000Z", "speed": 20.166885971952908, "timeD": "", "dbscan": "noise", "dateStr": "2017-09-05T04:26:37.000Z", "timestamp": 1504585597, "timeDelta": 874}, "geometry": {"type": "Point", "coordinates": [-80.16869794, 26.01718904]}}, {"type": "Feature", "properties": {"tweetID": "904926283074863105", "user": "IslesMarina", "text": "I'm at @Shell_us in Fort Lauderdale, FL https://t.co/tlF2cmKFqg", "date": "2017-09-05T04:36:53.000Z", "speed": 47.46001435892359, "timeD": "", "dbscan": "noise", "dateStr": "2017-09-05T04:36:53.000Z", "timestamp": 1504586213, "timeDelta": 616}, "geometry": {"type": "Point", "coordinates": [-80.15030401, 26.13352049]}}, {"type": "Feature", "properties": {"tweetID": "904928162123001856", "user": "IslesMarina", "text": "I'm at @Shell_us in Fort Lauderdale, FL https://t.co/83tM0JpHKB", "date": "2017-09-05T04:44:21.000Z", "speed": 0, "timeD": "", "dbscan": "noise", "dateStr": "2017-09-05T04:44:21.000Z", "timestamp": 1504586661, "timeDelta": 448}, "geometry": {"type": "Point", "coordinates": [-80.15030401, 26.13352049]}}, {"type": "Feature", "properties": {"tweetID": "904936038325518337", "user": "IslesMarina", "text": "I'm at Northside Church of Christ in Fort Lauderdale, FL https://t.co/TJu7I5D8nY", "date": "2017-09-05T05:15:39.000Z", "speed": 2.868809009064107, "timeD": "", "dbscan": "noise", "dateStr": "2017-09-05T05:15:39.000Z", "timestamp": 1504588539, "timeDelta": 1878}, "geometry": {"type": "Point", "coordinates": [-80.16049531, 26.15314606]}}, {"type": "Feature", "properties": {"tweetID": "904948369474322432", "user": "IslesMarina", "text": "I'm at Mills Pond Park in Wilton Manors, FL https://t.co/IP6j3jNpLc", "date": "2017-09-05T06:04:39.000Z", "speed": 0.36516649221391767, "timeD": "", "dbscan": "noise", "dateStr": "2017-09-05T06:04:39.000Z", "timestamp": 1504591479, "timeDelta": 2940}, "geometry": {"type": "Point", "coordinates": [-80.1609259, 26.15744354]}}, {"type": "Feature", "properties": {"tweetID": "904949248449548288", "user": "IslesMarina", "text": "I'm at @7Eleven in Miami, FL https://t.co/jmlq1sQFHD", "date": "2017-09-05T06:08:08.000Z", "speed": 230.44482617661845, "timeD": "", "dbscan": "noise", "dateStr": "2017-09-05T06:08:08.000Z", "timestamp": 1504591688, "timeDelta": 209}, "geometry": {"type": "Point", "coordinates": [-80.17068118, 25.96407195]}}, {"type": "Feature", "properties": {"tweetID": "905180017772126209", "user": "IslesMarina", "text": "I'm at County Line &amp; 441 https://t.co/5Y90jeMicR", "date": "2017-09-05T21:25:08.000Z", "speed": 0.1491970800737902, "timeD": "", "dbscan": "noise", "dateStr": "2017-09-05T21:25:08.000Z", "timestamp": 1504646708, "timeDelta": 55020}, "geometry": {"type": "Point", "coordinates": [-80.20608215, 25.97276202]}}, {"type": "Feature", "properties": {"tweetID": "905217015308308480", "user": "IslesMarina", "text": "I'm at Wright And Young Funeral Home in Miami, FL https://t.co/hfKjuZal9B", "date": "2017-09-05T23:52:09.000Z", "speed": 1.6261210371446926, "timeD": "", "dbscan": "noise", "dateStr": "2017-09-05T23:52:09.000Z", "timestamp": 1504655529, "timeDelta": 8821}, "geometry": {"type": "Point", "coordinates": [-80.21222138, 25.91537744]}}, {"type": "Feature", "properties": {"tweetID": "905230367174651904", "user": "IslesMarina", "text": "I'm at @Publix in North Miami Beach, FL https://t.co/zkPiZt2tXv", "date": "2017-09-06T00:45:12.000Z", "speed": 3.9690347047922274, "timeD": "", "cluster": 3, "dbscan": "core", "dateStr": "2017-09-06T00:45:12.000Z", "timestamp": 1504658712, "timeDelta": 3183}, "geometry": {"type": "Point", "coordinates": [-80.167061, 25.94585]}}, {"type": "Feature", "properties": {"tweetID": "905231214923194368", "user": "IslesMarina", "text": "I'm at Chase Bank - @chasesupport in North Miami Beach, FL https://t.co/dcZcMvK0Ku", "date": "2017-09-06T00:48:34.000Z", "speed": 3.4916617687742013, "timeD": "", "cluster": 3, "dbscan": "core", "dateStr": "2017-09-06T00:48:34.000Z", "timestamp": 1504658914, "timeDelta": 202}, "geometry": {"type": "Point", "coordinates": [-80.164246, 25.944574]}}, {"type": "Feature", "properties": {"tweetID": "905231358888476672", "user": "IslesMarina", "text": "I'm at @Redbox in North Miami Beach, FL https://t.co/v1dSOw9ScZ", "date": "2017-09-06T00:49:09.000Z", "speed": 20.151876494068247, "timeD": "", "cluster": 3, "dbscan": "core", "dateStr": "2017-09-06T00:49:09.000Z", "timestamp": 1504658949, "timeDelta": 35}, "geometry": {"type": "Point", "coordinates": [-80.167061, 25.94585]}}, {"type": "Feature", "properties": {"tweetID": "905231502895714306", "user": "IslesMarina", "text": "I'm at Starbucks in Miami, FL https://t.co/RztIQOZKm7", "date": "2017-09-06T00:49:43.000Z", "speed": 3.0921942447066164, "timeD": "", "cluster": 3, "dbscan": "core", "dateStr": "2017-09-06T00:49:43.000Z", "timestamp": 1504658983, "timeDelta": 34}, "geometry": {"type": "Point", "coordinates": [-80.16742636, 25.94558428]}}, {"type": "Feature", "properties": {"tweetID": "905231789324734466", "user": "IslesMarina", "text": "I'm at @CubanGuys in North Miami Beach, FL https://t.co/9uPjf44ASB", "date": "2017-09-06T00:50:51.000Z", "speed": 2.9462869963378493, "timeD": "", "cluster": 3, "dbscan": "core", "dateStr": "2017-09-06T00:50:51.000Z", "timestamp": 1504659051, "timeDelta": 68}, "geometry": {"type": "Point", "coordinates": [-80.16697573, 25.94488846]}}, {"type": "Feature", "properties": {"tweetID": "905231932681834496", "user": "IslesMarina", "text": "I'm at Roasters' n Toasters - @kaifers in North Miami Beach, FL https://t.co/Jm3s3oPwVZ", "date": "2017-09-06T00:51:25.000Z", "speed": 21.976709345598547, "timeD": "", "cluster": 3, "dbscan": "core", "dateStr": "2017-09-06T00:51:25.000Z", "timestamp": 1504659085, "timeDelta": 34}, "geometry": {"type": "Point", "coordinates": [-80.16409803, 25.94641244]}}, {"type": "Feature", "properties": {"tweetID": "905232163590873095", "user": "IslesMarina", "text": "I'm at Goodwill in Miami, FL https://t.co/BtOrYhsdNn", "date": "2017-09-06T00:52:20.000Z", "speed": 6.625647929341589, "timeD": "", "cluster": 3, "dbscan": "core", "dateStr": "2017-09-06T00:52:20.000Z", "timestamp": 1504659140, "timeDelta": 55}, "geometry": {"type": "Point", "coordinates": [-80.164657, 25.9450368]}}, {"type": "Feature", "properties": {"tweetID": "905232985817047042", "user": "IslesMarina", "text": "I'm at Canada Pharmacy Rx in Aventura, FL https://t.co/HBnSik3lC0", "date": "2017-09-06T00:55:36.000Z", "speed": 31.545900697471506, "timeD": "", "cluster": 0, "dbscan": "core", "dateStr": "2017-09-06T00:55:36.000Z", "timestamp": 1504659336, "timeDelta": 196}, "geometry": {"type": "Point", "coordinates": [-80.14007092, 25.95638547]}}, {"type": "Feature", "properties": {"tweetID": "905235847225769984", "user": "IslesMarina", "text": "I'm at @McDonalds in Miami, FL https://t.co/s9j6SHihMw", "date": "2017-09-06T01:06:59.000Z", "speed": 8.795029450668196, "timeD": "", "cluster": 3, "dbscan": "core", "dateStr": "2017-09-06T01:06:59.000Z", "timestamp": 1504660019, "timeDelta": 683}, "geometry": {"type": "Point", "coordinates": [-80.16379281, 25.94507653]}}, {"type": "Feature", "properties": {"tweetID": "905251344793178113", "user": "IslesMarina", "text": "I'm at @Equinox Aventura in Aventura, FL https://t.co/2mi1oIrL9U", "date": "2017-09-06T02:08:34.000Z", "speed": 1.4481146837522303, "timeD": "", "cluster": 0, "dbscan": "core", "dateStr": "2017-09-06T02:08:34.000Z", "timestamp": 1504663714, "timeDelta": 3695}, "geometry": {"type": "Point", "coordinates": [-80.144219, 25.957434]}}, {"type": "Feature", "properties": {"tweetID": "905251573059788800", "user": "IslesMarina", "text": "I'm at Raw Juce in Aventura, FL https://t.co/G80bX9Mveh", "date": "2017-09-06T02:09:28.000Z", "speed": 15.210654281067269, "timeD": "", "cluster": 0, "dbscan": "core", "dateStr": "2017-09-06T02:09:28.000Z", "timestamp": 1504663768, "timeDelta": 54}, "geometry": {"type": "Point", "coordinates": [-80.14565228, 25.96047324]}}, {"type": "Feature", "properties": {"tweetID": "905251663627382785", "user": "IslesMarina", "text": "I'm at @DisneyStore in North Miami Beach, FL https://t.co/nc5bOFrsVv", "date": "2017-09-06T02:09:50.000Z", "speed": 34.55584823613396, "timeD": "", "cluster": 0, "dbscan": "core", "dateStr": "2017-09-06T02:09:50.000Z", "timestamp": 1504663790, "timeDelta": 22}, "geometry": {"type": "Point", "coordinates": [-80.14388099, 25.95786571]}}, {"type": "Feature", "properties": {"tweetID": "905251768443039744", "user": "IslesMarina", "text": "Hop on the bus.... GUS... Make a new plan... Stan... Just gotta get free... @skip7547... https://t.co/1BbMXKEKE4 https://t.co/OsmhGjal5K", "date": "2017-09-06T02:10:15.000Z", "speed": 6.7448198668595145, "timeD": "", "cluster": 0, "dbscan": "core", "dateStr": "2017-09-06T02:10:15.000Z", "timestamp": 1504663815, "timeDelta": 25}, "geometry": {"type": "Point", "coordinates": [-80.144399, 25.958358]}}, {"type": "Feature", "properties": {"tweetID": "905612291567222784", "user": "IslesMarina", "text": "I'm at Strike 10 in Hallandale, FL https://t.co/TgoCJymOSl", "date": "2017-09-07T02:02:50.000Z", "speed": 0.05612579310490844, "timeD": "", "dbscan": "noise", "dateStr": "2017-09-07T02:02:50.000Z", "timestamp": 1504749770, "timeDelta": 85955}, "geometry": {"type": "Point", "coordinates": [-80.14059863, 25.97744373]}}, {"type": "Feature", "properties": {"tweetID": "905662215503585280", "user": "IslesMarina", "text": "I'm at Mystic Pointe Tower 600 GYM in \u041c\u0430\u0439\u0430\u043c\u0438, FL https://t.co/My0HafXI9f", "date": "2017-09-07T05:21:13.000Z", "speed": 0.5375229966274454, "timeD": "", "cluster": 0, "dbscan": "core", "dateStr": "2017-09-07T05:21:13.000Z", "timestamp": 1504761673, "timeDelta": 11903}, "geometry": {"type": "Point", "coordinates": [-80.13208252, 25.95289552]}}, {"type": "Feature", "properties": {"tweetID": "905831611031314433", "user": "IslesMarina", "text": "I'm at Aventura Parc Central in Aventura, FL https://t.co/DfV8EklmGk", "date": "2017-09-07T16:34:20.000Z", "speed": 0.020763826656317524, "timeD": "", "cluster": 0, "dbscan": "core", "dateStr": "2017-09-07T16:34:20.000Z", "timestamp": 1504802060, "timeDelta": 40387}, "geometry": {"type": "Point", "coordinates": [-80.135704, 25.953765]}}, {"type": "Feature", "properties": {"tweetID": "905968605053018113", "user": "IslesMarina", "text": "I'm at @7Eleven in Sunny Isles Beach, FL https://t.co/xhZJvhT5Pt", "date": "2017-09-08T01:38:42.000Z", "speed": 0.1360611244413565, "timeD": "", "cluster": 0, "dbscan": "core", "dateStr": "2017-09-08T01:38:42.000Z", "timestamp": 1504834722, "timeDelta": 32662}, "geometry": {"type": "Point", "coordinates": [-80.12177061, 25.94103561]}}, {"type": "Feature", "properties": {"tweetID": "905968664884719616", "user": "IslesMarina", "text": "I'm at Exxon in Sunny Isles Beach, FL https://t.co/PoRy1qohen", "date": "2017-09-08T01:38:56.000Z", "speed": 1.4331357442365122, "timeD": "", "cluster": 0, "dbscan": "core", "dateStr": "2017-09-08T01:38:56.000Z", "timestamp": 1504834736, "timeDelta": 14}, "geometry": {"type": "Point", "coordinates": [-80.121736, 25.94111]}}, {"type": "Feature", "properties": {"tweetID": "905971248181719040", "user": "IslesMarina", "text": "I'm at Pirates Cove Sunny Isles in Sunny Isles Beach, FL https://t.co/iOk0s5kTWE", "date": "2017-09-08T01:49:12.000Z", "speed": 2.0693250911978684, "timeD": "", "cluster": 0, "dbscan": "core", "dateStr": "2017-09-08T01:49:12.000Z", "timestamp": 1504835352, "timeDelta": 616}, "geometry": {"type": "Point", "coordinates": [-80.124132, 25.936462]}}, {"type": "Feature", "properties": {"tweetID": "906195281913548800", "user": "IslesMarina", "text": "I'm at Town Center Park in Sunny Isles Beach, FL https://t.co/EvaZf8lXo2", "date": "2017-09-08T16:39:26.000Z", "speed": 0.009544400426834472, "timeD": "", "cluster": 0, "dbscan": "core", "dateStr": "2017-09-08T16:39:26.000Z", "timestamp": 1504888766, "timeDelta": 53414}, "geometry": {"type": "Point", "coordinates": [-80.12198968, 25.93576447]}}, {"type": "Feature", "properties": {"tweetID": "906195325014216705", "user": "IslesMarina", "text": "Getting Ready For #HurricaneIrma (@ City of Sunny Isles Beach in FL) https://t.co/iX94Z2L2O5 https://t.co/qtXgQps0A8", "date": "2017-09-08T16:39:36.000Z", "speed": 369.16813677675475, "timeD": "", "cluster": 0, "dbscan": "core", "dateStr": "2017-09-08T16:39:36.000Z", "timestamp": 1504888776, "timeDelta": 10}, "geometry": {"type": "Point", "coordinates": [-80.12073755, 25.95055879]}}, {"type": "Feature", "properties": {"tweetID": "906232743951990784", "user": "IslesMarina", "text": "I'm at World Market &amp; Cafe in Hollywood, FL https://t.co/3PF4Mlp380", "date": "2017-09-08T19:08:17.000Z", "speed": 1.481839090673779, "timeD": "", "cluster": 2, "dbscan": "core", "dateStr": "2017-09-08T19:08:17.000Z", "timestamp": 1504897697, "timeDelta": 8921}, "geometry": {"type": "Point", "coordinates": [-80.142873, 25.99982142]}}, {"type": "Feature", "properties": {"tweetID": "906233000890859520", "user": "IslesMarina", "text": "I'm at Tastes of Europe in Hollywood, FL https://t.co/yBgH6uOmgB", "date": "2017-09-08T19:09:19.000Z", "speed": 1.3114971543069456, "timeD": "", "cluster": 2, "dbscan": "core", "dateStr": "2017-09-08T19:09:19.000Z", "timestamp": 1504897759, "timeDelta": 62}, "geometry": {"type": "Point", "coordinates": [-80.14299, 25.999512]}}, {"type": "Feature", "properties": {"tweetID": "906233059355357184", "user": "IslesMarina", "text": "I'm at @MoneyGram (in WORLD MARKET &amp; CAFE) in Hollywood, FL https://t.co/4XKFLd49PD", "date": "2017-09-08T19:09:33.000Z", "speed": 4.4793270337490325, "timeD": "", "cluster": 2, "dbscan": "core", "dateStr": "2017-09-08T19:09:33.000Z", "timestamp": 1504897773, "timeDelta": 14}, "geometry": {"type": "Point", "coordinates": [-80.14304644, 25.99975888]}}, {"type": "Feature", "properties": {"tweetID": "906281365548785664", "user": "IslesMarina", "text": "Still Open In Sunny Isles Beach, Florida \ud83c\udf34 #HurricaneIrma (@ Milam's Supermarket in Sunny Isles Beach, FL) https://t.co/yR3ehg53nF", "date": "2017-09-08T22:21:30.000Z", "speed": 1.465506786819825, "timeD": "", "cluster": 0, "dbscan": "core", "dateStr": "2017-09-08T22:21:30.000Z", "timestamp": 1504909290, "timeDelta": 11517}, "geometry": {"type": "Point", "coordinates": [-80.12319638, 25.93431373]}}, {"type": "Feature", "properties": {"tweetID": "906281417117716480", "user": "IslesMarina", "text": "I'm at @MuseSunnyIsles in Sunny Isles Beach, FL https://t.co/q9iBZdNw6v", "date": "2017-09-08T22:21:42.000Z", "speed": 28.638172677268887, "timeD": "", "cluster": 0, "dbscan": "core", "dateStr": "2017-09-08T22:21:42.000Z", "timestamp": 1504909302, "timeDelta": 12}, "geometry": {"type": "Point", "coordinates": [-80.12173339, 25.9347341]}}, {"type": "Feature", "properties": {"tweetID": "906281499347038209", "user": "IslesMarina", "text": "I'm at Wolsen Caffe in Sunny Isles Beach, FL https://t.co/xePTkrwWwB", "date": "2017-09-08T22:22:01.000Z", "speed": 6.379381875046472, "timeD": "", "cluster": 0, "dbscan": "core", "dateStr": "2017-09-08T22:22:01.000Z", "timestamp": 1504909321, "timeDelta": 19}, "geometry": {"type": "Point", "coordinates": [-80.122234, 25.934548]}}, {"type": "Feature", "properties": {"tweetID": "906281569584914433", "user": "IslesMarina", "text": "I'm at Jungle Juice Cafe in Sunny Isles Beach, FL https://t.co/kVsFm93gId", "date": "2017-09-08T22:22:18.000Z", "speed": 3.9530709469248784, "timeD": "", "cluster": 0, "dbscan": "core", "dateStr": "2017-09-08T22:22:18.000Z", "timestamp": 1504909338, "timeDelta": 17}, "geometry": {"type": "Point", "coordinates": [-80.12251101, 25.93444364]}}, {"type": "Feature", "properties": {"tweetID": "906281631048232961", "user": "IslesMarina", "text": "I'm at Starbucks in Sunny Isles Beach, FL https://t.co/VdKTho3bGx", "date": "2017-09-08T22:22:33.000Z", "speed": 8.593503270927663, "timeD": "", "cluster": 0, "dbscan": "core", "dateStr": "2017-09-08T22:22:33.000Z", "timestamp": 1504909353, "timeDelta": 15}, "geometry": {"type": "Point", "coordinates": [-80.12199844, 25.93468011]}}, {"type": "Feature", "properties": {"tweetID": "906290098689499138", "user": "IslesMarina", "text": "I'm at Soya Noodle Bar in Sunny Isles Beach, FL https://t.co/iXzVqWDz83", "date": "2017-09-08T22:56:12.000Z", "speed": 1.1111798719611776, "timeD": "", "cluster": 0, "dbscan": "core", "dateStr": "2017-09-08T22:56:12.000Z", "timestamp": 1504911372, "timeDelta": 2019}, "geometry": {"type": "Point", "coordinates": [-80.12161, 25.94369]}}, {"type": "Feature", "properties": {"tweetID": "906313326094901248", "user": "IslesMarina", "text": "I'm at Porsche Design: Tower Miami in Sunny Isles Beach, FL https://t.co/gj73qiz15B", "date": "2017-09-09T00:28:30.000Z", "speed": 0.1229315354400518, "timeD": "", "cluster": 0, "dbscan": "core", "dateStr": "2017-09-09T00:28:30.000Z", "timestamp": 1504916910, "timeDelta": 5538}, "geometry": {"type": "Point", "coordinates": [-80.12104632, 25.9463788]}}, {"type": "Feature", "properties": {"tweetID": "906313380042039296", "user": "IslesMarina", "text": "I'm at Sahara Beach Club in Sunny Isles Beach, FL https://t.co/lVbq7qN6sU", "date": "2017-09-09T00:28:42.000Z", "speed": 15.245282623817733, "timeD": "", "cluster": 0, "dbscan": "core", "dateStr": "2017-09-09T00:28:42.000Z", "timestamp": 1504916922, "timeDelta": 12}, "geometry": {"type": "Point", "coordinates": [-80.12024403, 25.94623682]}}, {"type": "Feature", "properties": {"tweetID": "906539189365329921", "user": "IslesMarina", "text": "Stay Safe During The Storm! \ud83c\udf2a #HurricaneIrma2017 (@ Waterway Realtors\u00ae 786-229-7999 - @waterwayrealty) https://t.co/TAZvaBhDIU", "date": "2017-09-09T15:26:00.000Z", "speed": 0.0029224270100554634, "timeD": "", "cluster": 0, "dbscan": "core", "dateStr": "2017-09-09T15:26:00.000Z", "timestamp": 1504970760, "timeDelta": 53838}, "geometry": {"type": "Point", "coordinates": [-80.12091155, 25.94603787]}}, {"type": "Feature", "properties": {"tweetID": "906539237960568832", "user": "IslesMarina", "text": "I'm at Virgin Hotspot 5G in Sunny Isles Beach, FL https://t.co/2PFMrAqkeF", "date": "2017-09-09T15:26:11.000Z", "speed": 36.23622169964086, "timeD": "", "cluster": 0, "dbscan": "core", "dateStr": "2017-09-09T15:26:11.000Z", "timestamp": 1504970771, "timeDelta": 11}, "geometry": {"type": "Point", "coordinates": [-80.121674, 25.94459]}}, {"type": "Feature", "properties": {"tweetID": "906631037912051712", "user": "IslesMarina", "text": "I'm at City of Sunny Isles Beach in FL https://t.co/1XPIZ4ZiG8", "date": "2017-09-09T21:30:58.000Z", "speed": 0.06852584662063711, "timeD": "", "cluster": 0, "dbscan": "core", "dateStr": "2017-09-09T21:30:58.000Z", "timestamp": 1504992658, "timeDelta": 21887}, "geometry": {"type": "Point", "coordinates": [-80.12073755, 25.95055879]}}, {"type": "Feature", "properties": {"tweetID": "906631202987274241", "user": "IslesMarina", "text": "I'm at PNC BANK in Sunny Isles Beach, FL https://t.co/kjDeQkyKAo", "date": "2017-09-09T21:31:37.000Z", "speed": 37.487829821463784, "timeD": "", "cluster": 0, "dbscan": "core", "dateStr": "2017-09-09T21:31:37.000Z", "timestamp": 1504992697, "timeDelta": 39}, "geometry": {"type": "Point", "coordinates": [-80.121647, 25.94474]}}, {"type": "Feature", "properties": {"tweetID": "906631400006340608", "user": "IslesMarina", "text": "I'm at Furniture Lights And D\u00e9cor in Sunny Isles Beach, FL https://t.co/r05d0sxxtA", "date": "2017-09-09T21:32:24.000Z", "speed": 1.7807205906665386, "timeD": "", "cluster": 0, "dbscan": "core", "dateStr": "2017-09-09T21:32:24.000Z", "timestamp": 1504992744, "timeDelta": 47}, "geometry": {"type": "Point", "coordinates": [-80.121784, 25.944427]}}, {"type": "Feature", "properties": {"tweetID": "906631790969925632", "user": "IslesMarina", "text": "I'm at Trump Grande in Sunny Isles Beach, FL https://t.co/SMTZqiEvZF", "date": "2017-09-09T21:33:58.000Z", "speed": 3.4262078538355443, "timeD": "", "cluster": 0, "dbscan": "core", "dateStr": "2017-09-09T21:33:58.000Z", "timestamp": 1504992838, "timeDelta": 94}, "geometry": {"type": "Point", "coordinates": [-80.12099724, 25.94551095]}}, {"type": "Feature", "properties": {"tweetID": "906661886380462083", "user": "IslesMarina", "text": "I'm at Sherwin-Williams Paint in Sunny Isles Beach, FL https://t.co/dJA4bPl5c7", "date": "2017-09-09T23:33:33.000Z", "speed": 0.03603737058837928, "timeD": "", "cluster": 0, "dbscan": "core", "dateStr": "2017-09-09T23:33:33.000Z", "timestamp": 1505000013, "timeDelta": 7175}, "geometry": {"type": "Point", "coordinates": [-80.121984, 25.94497]}}, {"type": "Feature", "properties": {"tweetID": "906709364224008193", "user": "IslesMarina", "text": "I'm at Trump Royale in Sunny Isles Beach, FL https://t.co/4FaD3ngqSa https://t.co/175bX6gwcZ", "date": "2017-09-10T02:42:12.000Z", "speed": 0.03454522596879136, "timeD": "", "cluster": 0, "dbscan": "core", "dateStr": "2017-09-10T02:42:12.000Z", "timestamp": 1505011332, "timeDelta": 11319}, "geometry": {"type": "Point", "coordinates": [-80.1202938, 25.94457034]}}, {"type": "Feature", "properties": {"tweetID": "906709395970641921", "user": "IslesMarina", "text": "I'm at RESIDENCES BY ARMANI in Sunny Isles Beach, FL https://t.co/WPo4XPX0Dh", "date": "2017-09-10T02:42:20.000Z", "speed": 33.85329834428849, "timeD": "", "cluster": 0, "dbscan": "core", "dateStr": "2017-09-10T02:42:20.000Z", "timestamp": 1505011340, "timeDelta": 8}, "geometry": {"type": "Point", "coordinates": [-80.11979211, 25.94556092]}}, {"type": "Feature", "properties": {"tweetID": "906709453000642560", "user": "IslesMarina", "text": "I'm at Dolce Vita Gelato Cafe Sunny Isles - @dolcevitausa in Sunny Isles Beach, FL https://t.co/FzmbdjbOGl", "date": "2017-09-10T02:42:34.000Z", "speed": 31.286384080314992, "timeD": "", "cluster": 0, "dbscan": "core", "dateStr": "2017-09-10T02:42:34.000Z", "timestamp": 1505011354, "timeDelta": 14}, "geometry": {"type": "Point", "coordinates": [-80.12172684, 25.94529203]}}, {"type": "Feature", "properties": {"tweetID": "906958641340796929", "user": "IslesMarina", "text": "I'm at City of Sunny Isles Beach in FL https://t.co/0w6wZYaSwp", "date": "2017-09-10T19:12:45.000Z", "speed": 0.022369676018409057, "timeD": "", "cluster": 0, "dbscan": "core", "dateStr": "2017-09-10T19:12:45.000Z", "timestamp": 1505070765, "timeDelta": 59411}, "geometry": {"type": "Point", "coordinates": [-80.12073755, 25.95055879]}}, {"type": "Feature", "properties": {"tweetID": "907043822374354950", "user": "IslesMarina", "text": "I'm at Trump Royale in Sunny Isles Beach, FL https://t.co/xRdy30LZvX", "date": "2017-09-11T00:51:13.000Z", "speed": 0.07353333552623663, "timeD": "", "cluster": 0, "dbscan": "core", "dateStr": "2017-09-11T00:51:13.000Z", "timestamp": 1505091073, "timeDelta": 20308}, "geometry": {"type": "Point", "coordinates": [-80.1202938, 25.94457034]}}, {"type": "Feature", "properties": {"tweetID": "907254447314743298", "user": "IslesMarina", "text": "I'm at Virgin Hotspot 5G in Sunny Isles Beach, FL https://t.co/Q6ItTong87", "date": "2017-09-11T14:48:10.000Z", "speed": 0.006150148681704168, "timeD": "", "cluster": 0, "dbscan": "core", "dateStr": "2017-09-11T14:48:10.000Z", "timestamp": 1505141290, "timeDelta": 50217}, "geometry": {"type": "Point", "coordinates": [-80.121674, 25.94459]}}, {"type": "Feature", "properties": {"tweetID": "907254571894009857", "user": "IslesMarina", "text": "I'm at Porsche Design: Tower Miami in Sunny Isles Beach, FL https://t.co/9mwT8HHpPG", "date": "2017-09-11T14:48:40.000Z", "speed": 15.556956908714742, "timeD": "", "cluster": 0, "dbscan": "core", "dateStr": "2017-09-11T14:48:40.000Z", "timestamp": 1505141320, "timeDelta": 30}, "geometry": {"type": "Point", "coordinates": [-80.12104632, 25.9463788]}}, {"type": "Feature", "properties": {"tweetID": "907254627921522688", "user": "IslesMarina", "text": "I'm at Ramada Plaza @MarcoPoloBeach Resort in North Miami Beach, FL https://t.co/AyCRGuM3BO", "date": "2017-09-11T14:48:53.000Z", "speed": 155.75519355007057, "timeD": "", "cluster": 0, "dbscan": "core", "dateStr": "2017-09-11T14:48:53.000Z", "timestamp": 1505141333, "timeDelta": 13}, "geometry": {"type": "Point", "coordinates": [-80.119783, 25.954437]}}, {"type": "Feature", "properties": {"tweetID": "907254675208056833", "user": "IslesMarina", "text": "I'm at Miami Juice in Sunny Isles Beach, FL https://t.co/pD2vns4jt8", "date": "2017-09-11T14:49:05.000Z", "speed": 116.02524702925318, "timeD": "", "cluster": 0, "dbscan": "core", "dateStr": "2017-09-11T14:49:05.000Z", "timestamp": 1505141345, "timeDelta": 12}, "geometry": {"type": "Point", "coordinates": [-80.1209209, 25.94893558]}}, {"type": "Feature", "properties": {"tweetID": "907254759949836291", "user": "IslesMarina", "text": "I'm at @AcqualinaResort &amp; Spa On The Beach in Sunny Isles Beach, FL https://t.co/v6BIyCPeiH", "date": "2017-09-11T14:49:25.000Z", "speed": 101.61046752564665, "timeD": "", "cluster": 0, "dbscan": "core", "dateStr": "2017-09-11T14:49:25.000Z", "timestamp": 1505141365, "timeDelta": 20}, "geometry": {"type": "Point", "coordinates": [-80.12046911, 25.94077811]}}, {"type": "Feature", "properties": {"tweetID": "907264417783582725", "user": "IslesMarina", "text": "We Are Still Here! \ud83c\uddfa\ud83c\uddf8 Stronger Than #HurricaneIrma \ud83c\udf2a Today Is 9/11 #NeverForget https://t.co/vUTaqUpSV2 https://t.co/MzOcZA7C8P", "date": "2017-09-11T15:27:48.000Z", "speed": 0.5698832948725985, "timeD": "", "cluster": 0, "dbscan": "core", "dateStr": "2017-09-11T15:27:48.000Z", "timestamp": 1505143668, "timeDelta": 2303}, "geometry": {"type": "Point", "coordinates": [-80.12091155, 25.94603787]}}, {"type": "Feature", "properties": {"tweetID": "907292892603002880", "user": "IslesMarina", "text": "I'm at Bank of America in Sunny Isles Beach, FL https://t.co/bBzF2NLMUC", "date": "2017-09-11T17:20:56.000Z", "speed": 0.16981866907574913, "timeD": "", "cluster": 0, "dbscan": "core", "dateStr": "2017-09-11T17:20:56.000Z", "timestamp": 1505150456, "timeDelta": 6788}, "geometry": {"type": "Point", "coordinates": [-80.12243137, 25.94161114]}}, {"type": "Feature", "properties": {"tweetID": "907292976224854016", "user": "IslesMarina", "text": "I'm at Starbucks in Sunny Isles Beach, FL https://t.co/q3l5QG7jy9", "date": "2017-09-11T17:21:16.000Z", "speed": 86.36283412086496, "timeD": "", "cluster": 0, "dbscan": "core", "dateStr": "2017-09-11T17:21:16.000Z", "timestamp": 1505150476, "timeDelta": 20}, "geometry": {"type": "Point", "coordinates": [-80.12199844, 25.93468011]}}, {"type": "Feature", "properties": {"tweetID": "907332520626278400", "user": "IslesMarina", "text": "I'm at Rebekah\u2019 Nails in Sunny Isles Beach, FL https://t.co/SWG81WqjCS", "date": "2017-09-11T19:58:24.000Z", "speed": 0.11266056395007912, "timeD": "", "cluster": 0, "dbscan": "core", "dateStr": "2017-09-11T19:58:24.000Z", "timestamp": 1505159904, "timeDelta": 9428}, "geometry": {"type": "Point", "coordinates": [-80.121528, 25.938928]}}, {"type": "Feature", "properties": {"tweetID": "907345078800322567", "user": "IslesMarina", "text": "Exxon Gas and @7Eleven In Sunny Isles Beach Is Now Open! (at @7Eleven) https://t.co/aK5e7qELtE https://t.co/6qL6kjMsca", "date": "2017-09-11T20:48:19.000Z", "speed": 0.1760284551100688, "timeD": "", "cluster": 0, "dbscan": "core", "dateStr": "2017-09-11T20:48:19.000Z", "timestamp": 1505162899, "timeDelta": 2995}, "geometry": {"type": "Point", "coordinates": [-80.12177061, 25.94103561]}}, {"type": "Feature", "properties": {"tweetID": "907376901592944640", "user": "IslesMarina", "text": "I'm at City of Sunny Isles Beach in FL https://t.co/ceIsqDRVaF", "date": "2017-09-11T22:54:46.000Z", "speed": 0.3137930689487027, "timeD": "", "cluster": 0, "dbscan": "core", "dateStr": "2017-09-11T22:54:46.000Z", "timestamp": 1505170486, "timeDelta": 7587}, "geometry": {"type": "Point", "coordinates": [-80.12073755, 25.95055879]}}, {"type": "Feature", "properties": {"tweetID": "907376979795685376", "user": "IslesMarina", "text": "I'm at Sunny Isles Beach Community School in Sunny Isles Beach, FL https://t.co/5ANcXnCC2V", "date": "2017-09-11T22:55:04.000Z", "speed": 90.87704693632482, "timeD": "", "cluster": 0, "dbscan": "core", "dateStr": "2017-09-11T22:55:04.000Z", "timestamp": 1505170504, "timeDelta": 18}, "geometry": {"type": "Point", "coordinates": [-80.12327112, 25.9443918]}}, {"type": "Feature", "properties": {"tweetID": "907593282401832961", "user": "IslesMarina", "text": "I'm at Town Center Park in Sunny Isles Beach, FL https://t.co/SGWRInAMD8", "date": "2017-09-12T13:14:35.000Z", "speed": 0.041993857644177714, "timeD": "", "cluster": 0, "dbscan": "core", "dateStr": "2017-09-12T13:14:35.000Z", "timestamp": 1505222075, "timeDelta": 51571}, "geometry": {"type": "Point", "coordinates": [-80.12198968, 25.93576447]}}, {"type": "Feature", "properties": {"tweetID": "907594172626079744", "user": "IslesMarina", "text": "Not Open Yet \ud83c\udf00 #HurricaneIrma \ud83c\udf2a @Starbucks \u2615\ufe0f Sunny Isles Beach @RKCenters (@ Starbucks) https://t.co/jW3bRcUbnJ https://t.co/JrbBOlSNVQ", "date": "2017-09-12T13:18:07.000Z", "speed": 1.2726944280202068, "timeD": "", "cluster": 0, "dbscan": "core", "dateStr": "2017-09-12T13:18:07.000Z", "timestamp": 1505222287, "timeDelta": 212}, "geometry": {"type": "Point", "coordinates": [-80.12199844, 25.93468011]}}, {"type": "Feature", "properties": {"tweetID": "907594202644664321", "user": "IslesMarina", "text": "I'm at Moon Over Miami in North Miami Beach, FL https://t.co/KZUF4SmR2v", "date": "2017-09-12T13:18:14.000Z", "speed": 115.09929590641666, "timeD": "", "cluster": 0, "dbscan": "core", "dateStr": "2017-09-12T13:18:14.000Z", "timestamp": 1505222294, "timeDelta": 7}, "geometry": {"type": "Point", "coordinates": [-80.12468886, 25.93683227]}}, {"type": "Feature", "properties": {"tweetID": "907594270906966016", "user": "IslesMarina", "text": "I'm at Milam's Supermarket in Sunny Isles Beach, FL https://t.co/lsghmxoPJL", "date": "2017-09-12T13:18:31.000Z", "speed": 41.769297578798756, "timeD": "", "cluster": 0, "dbscan": "core", "dateStr": "2017-09-12T13:18:31.000Z", "timestamp": 1505222311, "timeDelta": 17}, "geometry": {"type": "Point", "coordinates": [-80.12319638, 25.93431373]}}, {"type": "Feature", "properties": {"tweetID": "907598741695291393", "user": "IslesMarina", "text": "I'm at Bellagio-Winston Bridge in Sunny Isles Beach, FL https://t.co/c9CC24hg8d", "date": "2017-09-12T13:36:17.000Z", "speed": 0.8167272552720664, "timeD": "", "cluster": 0, "dbscan": "core", "dateStr": "2017-09-12T13:36:17.000Z", "timestamp": 1505223377, "timeDelta": 1066}, "geometry": {"type": "Point", "coordinates": [-80.126579, 25.936043]}}, {"type": "Feature", "properties": {"tweetID": "907598807222947840", "user": "IslesMarina", "text": "I'm at Gilbert Samson Park in Sunny Isles Beach, FL https://t.co/QysnF8mVRY", "date": "2017-09-12T13:36:32.000Z", "speed": 85.8158204310792, "timeD": "", "cluster": 0, "dbscan": "core", "dateStr": "2017-09-12T13:36:32.000Z", "timestamp": 1505223392, "timeDelta": 15}, "geometry": {"type": "Point", "coordinates": [-80.121225, 25.937936]}}, {"type": "Feature", "properties": {"tweetID": "907598869583876097", "user": "IslesMarina", "text": "I'm at Monaco Banana Beach Bar in Sunny Isles Beach, FL https://t.co/U0TyZ8LIfn", "date": "2017-09-12T13:36:47.000Z", "speed": 11.630382011280131, "timeD": "", "cluster": 0, "dbscan": "core", "dateStr": "2017-09-12T13:36:47.000Z", "timestamp": 1505223407, "timeDelta": 15}, "geometry": {"type": "Point", "coordinates": [-80.12143893, 25.93861024]}}, {"type": "Feature", "properties": {"tweetID": "907644253714743296", "user": "IslesMarina", "text": "I'm at City of Sunny Isles Beach in FL https://t.co/a5thWc2mgN", "date": "2017-09-12T16:37:07.000Z", "speed": 0.2751485093635991, "timeD": "", "cluster": 0, "dbscan": "core", "dateStr": "2017-09-12T16:37:07.000Z", "timestamp": 1505234227, "timeDelta": 10820}, "geometry": {"type": "Point", "coordinates": [-80.12073755, 25.95055879]}}, {"type": "Feature", "properties": {"tweetID": "907670751259582464", "user": "IslesMarina", "text": "I'm at Starbucks in Sunny Isles Beach, FL https://t.co/A7O6pyxkOu", "date": "2017-09-12T18:22:25.000Z", "speed": 0.6269230111634525, "timeD": "", "cluster": 0, "dbscan": "core", "dateStr": "2017-09-12T18:22:25.000Z", "timestamp": 1505240545, "timeDelta": 6318}, "geometry": {"type": "Point", "coordinates": [-80.12199844, 25.93468011]}}, {"type": "Feature", "properties": {"tweetID": "907727051297366018", "user": "IslesMarina", "text": "I'm at @MuseSunnyIsles in Sunny Isles Beach, FL https://t.co/fBMZMughM5", "date": "2017-09-12T22:06:08.000Z", "speed": 0.004530217749320039, "timeD": "", "cluster": 0, "dbscan": "core", "dateStr": "2017-09-12T22:06:08.000Z", "timestamp": 1505253968, "timeDelta": 13423}, "geometry": {"type": "Point", "coordinates": [-80.12173339, 25.9347341]}}, {"type": "Feature", "properties": {"tweetID": "907727804137164800", "user": "IslesMarina", "text": "I'm at City of Sunny Isles Beach in FL https://t.co/aoz0JcPMTo", "date": "2017-09-12T22:09:07.000Z", "speed": 22.0318760181468, "timeD": "", "cluster": 0, "dbscan": "core", "dateStr": "2017-09-12T22:09:07.000Z", "timestamp": 1505254147, "timeDelta": 179}, "geometry": {"type": "Point", "coordinates": [-80.12073755, 25.95055879]}}, {"type": "Feature", "properties": {"tweetID": "907728301917163521", "user": "IslesMarina", "text": "I'm at Virgin Hotspot 5G in Sunny Isles Beach, FL https://t.co/8VPIGdiwNm", "date": "2017-09-12T22:11:06.000Z", "speed": 12.603573151141887, "timeD": "", "cluster": 0, "dbscan": "core", "dateStr": "2017-09-12T22:11:06.000Z", "timestamp": 1505254266, "timeDelta": 119}, "geometry": {"type": "Point", "coordinates": [-80.121674, 25.94459]}}, {"type": "Feature", "properties": {"tweetID": "907728504850190336", "user": "IslesMarina", "text": "I'm at Jungle Juice Cafe in Sunny Isles Beach, FL https://t.co/5WBx0Oiejc", "date": "2017-09-12T22:11:54.000Z", "speed": 52.73947376559966, "timeD": "", "cluster": 0, "dbscan": "core", "dateStr": "2017-09-12T22:11:54.000Z", "timestamp": 1505254314, "timeDelta": 48}, "geometry": {"type": "Point", "coordinates": [-80.12251101, 25.93444364]}}, {"type": "Feature", "properties": {"tweetID": "907728696563335168", "user": "IslesMarina", "text": "Open @Walgreens In Sunny Isles Beach, Florida (at @Walgreens in Sunny Isles Beach, FL) https://t.co/aG2AOsZmQg", "date": "2017-09-12T22:12:40.000Z", "speed": 20.739889941044236, "timeD": "", "cluster": 0, "dbscan": "core", "dateStr": "2017-09-12T22:12:40.000Z", "timestamp": 1505254360, "timeDelta": 46}, "geometry": {"type": "Point", "coordinates": [-80.12191059, 25.93823976]}}, {"type": "Feature", "properties": {"tweetID": "907728764028817411", "user": "IslesMarina", "text": "I'm at Santa Fe News &amp; Espresso SIB in Sunny Isles Beach, FL https://t.co/o94bIkE9BT", "date": "2017-09-12T22:12:56.000Z", "speed": 50.32418720860921, "timeD": "", "cluster": 0, "dbscan": "core", "dateStr": "2017-09-12T22:12:56.000Z", "timestamp": 1505254376, "timeDelta": 16}, "geometry": {"type": "Point", "coordinates": [-80.122074, 25.935007]}}, {"type": "Feature", "properties": {"tweetID": "907740063395717121", "user": "IslesMarina", "text": "I'm at Milam's Supermarket in Sunny Isles Beach, FL https://t.co/KT8Sm0OQeD", "date": "2017-09-12T22:57:50.000Z", "speed": 0.11309344834582226, "timeD": "", "cluster": 0, "dbscan": "core", "dateStr": "2017-09-12T22:57:50.000Z", "timestamp": 1505257070, "timeDelta": 2694}, "geometry": {"type": "Point", "coordinates": [-80.12319638, 25.93431373]}}, {"type": "Feature", "properties": {"tweetID": "907740456464863232", "user": "IslesMarina", "text": "I'm at Liquors And Fine Wines https://t.co/ynrPl4Dl6Q", "date": "2017-09-12T22:59:24.000Z", "speed": 2.452110981914381, "timeD": "", "cluster": 0, "dbscan": "core", "dateStr": "2017-09-12T22:59:24.000Z", "timestamp": 1505257164, "timeDelta": 94}, "geometry": {"type": "Point", "coordinates": [-80.12216963, 25.93438867]}}, {"type": "Feature", "properties": {"tweetID": "907740649436405760", "user": "IslesMarina", "text": "I'm at Simon's Footwear in Sunny Isles Beach, FL https://t.co/ie3OuDcbJY", "date": "2017-09-12T23:00:10.000Z", "speed": 4.044475114010583, "timeD": "", "cluster": 0, "dbscan": "core", "dateStr": "2017-09-12T23:00:10.000Z", "timestamp": 1505257210, "timeDelta": 46}, "geometry": {"type": "Point", "coordinates": [-80.121802, 25.933718]}}]}}