{"user": "rossydsousa", "meta": {"type": "FeatureCollection", "features": [{"type": "Feature", "properties": {"cluster": 0, "clusterCenter": true, "tweetCount": 6, "likelyHome": true, "likelyWork": true}, "geometry": {"type": "Point", "coordinates": [-69.9833, 18.5]}}]}, "tweets": {"type": "FeatureCollection", "features": [{"type": "Feature", "properties": {"tweetID": "903808354216267777", "user": "rossydsousa", "text": "Buenas noches mi ni\u00f1a bonita @marjodsousa que descanses millones de besos\ud83d\udc8b al Pr\u00edncipe hermoso\u2026 https://t.co/eUtglXO2Yv", "date": "2017-09-02T02:34:38.000Z", "speed": "", "timeD": "", "cluster": 0, "dbscan": "core", "dateStr": "2017-09-02T02:34:38.000Z", "timestamp": 1504319678}, "geometry": {"type": "Point", "coordinates": [-69.9833, 18.5]}}, {"type": "Feature", "properties": {"tweetID": "905830202676301824", "user": "rossydsousa", "text": "Ya ves mi bonita te amamos un mundo #Repost @mariaconchita_a with @repostapp\n\u30fb\u30fb\u30fb\nAmiga\u2026 https://t.co/EejtNTgPek", "date": "2017-09-07T16:28:44.000Z", "speed": 0, "timeD": "", "cluster": 0, "dbscan": "core", "dateStr": "2017-09-07T16:28:44.000Z", "timestamp": 1504801724, "timeDelta": 482046}, "geometry": {"type": "Point", "coordinates": [-69.9833, 18.5]}}, {"type": "Feature", "properties": {"tweetID": "905845214765514753", "user": "rossydsousa", "text": "Bajo su protecci\u00f3n s\u00edempre #MarjoyMatiSiempreJuntos @marjodsousa #MatiasGregorio\u2026 https://t.co/KhBIqdzuZw", "date": "2017-09-07T17:28:23.000Z", "speed": 0, "timeD": "", "cluster": 0, "dbscan": "core", "dateStr": "2017-09-07T17:28:23.000Z", "timestamp": 1504805303, "timeDelta": 3579}, "geometry": {"type": "Point", "coordinates": [-69.9833, 18.5]}}, {"type": "Feature", "properties": {"tweetID": "905845324719239170", "user": "rossydsousa", "text": "Dios y la Virgen estan con Tigo @marjodsousa  cuidandote y protegiendote al igual que a Mati en\u2026 https://t.co/VfgzSnkpEC", "date": "2017-09-07T17:28:49.000Z", "speed": 0, "timeD": "", "cluster": 0, "dbscan": "core", "dateStr": "2017-09-07T17:28:49.000Z", "timestamp": 1504805329, "timeDelta": 26}, "geometry": {"type": "Point", "coordinates": [-69.9833, 18.5]}}, {"type": "Feature", "properties": {"tweetID": "905850450997428224", "user": "rossydsousa", "text": "#sousaticosunidos por una sola causa tu @marjodsousa y por Mati en Santo Domingo, Dominican\u2026 https://t.co/4rHXaqIDcj", "date": "2017-09-07T17:49:12.000Z", "speed": 0, "timeD": "", "cluster": 0, "dbscan": "core", "dateStr": "2017-09-07T17:49:12.000Z", "timestamp": 1504806552, "timeDelta": 1223}, "geometry": {"type": "Point", "coordinates": [-69.9833, 18.5]}}, {"type": "Feature", "properties": {"tweetID": "905850486846365696", "user": "rossydsousa", "text": "Tu @marjodsousa eres nuestra  Fuerza mayor #EstamosConTigoMDS #FuerzaMarjo @LightConceptsPR\u2026 https://t.co/EOTU8PP37s", "date": "2017-09-07T17:49:20.000Z", "speed": 0, "timeD": "", "cluster": 0, "dbscan": "core", "dateStr": "2017-09-07T17:49:20.000Z", "timestamp": 1504806560, "timeDelta": 8}, "geometry": {"type": "Point", "coordinates": [-69.9833, 18.5]}}]}}